Workbook

Sheet format
A1: 股票代码 | B1: 公司名称 | C1: 报告名称 | D1: 总股本（亿） | E1: 分红（HKD） | F1: 营业收入（亿RMB） | G1: 营业成本（亿RMB） | H1: 营业利润（亿RMB） | I1: 净利润（亿RMB） | J1: 归母利润（亿RMB） | K1: 扣非利润（亿RMB） | L1: 销售费用（亿RMB） | M1: 管理费用（亿RMB） | N1: 研发费用（亿RMB） | O1: 融资成本（亿RMB） | P1: 货币资金（亿RMB） | Q1: 应收（亿RMB） | R1: 库存（亿RMB） | S1: 投资（亿RMB） | T1: 应付（亿RMB） | U1: 短期贷款（亿RMB） | V1: 长期贷款（亿RMB） | W1: 总资产（亿RMB） | X1: 净资产（亿RMB） | Y1: 非流动资产（亿RMB） | Z1: 流动负债（亿RMB） | AA1: 经营现金流净额（亿RMB） | AB1: 资本开支（亿RMB）
A2: 700 | B2: 腾讯控股 | C2: 2023年报 | D2: 93.42 | E2: 3.4 | F2: 6090 | G2: 3159 | H2: 1517 | I2: 1180 | J2: 1152 | K2: 1577 | L2: 342 | M2: 1035 | N2: 641 | O2: 127 | P2: =3621+208 -> 3829 | Q2: 466 | R2: 4.6 | S2: 6893 | T2: 1152 | U2: 477 | V2: 3094 | W2: 15800 | X2: 8737 | Y2: 10600 | Z2: 3522 | AA2: 2220 | AB2: 622
A3: 700 | B3: 腾讯控股 | C3: 2024年报 | D3: 91.79 | E3: 4.5 | F3: 6603 | G3: 3110 | H3: 2035 | I3: 1965 | J3: 1940 | K3: 2227 | L3: 364 | M3: 1148 | N3: 707 | O3: 120 | P3: 4760 | Q3: 482 | R3: 4.4 | S3: =6534+3389 -> 9923 | T3: 1273 | U3: 947 | V3: 2910 | W3: 17800 | X3: 10500 | Y3: 12800 | Z3: 3969 | AA3: 2585 | AB3: 960

Sheet Raw
B1: 报告名称 | C1: 港股股价 | D1: 人民币股价 | E1: 总股本 | F1: 净资产 | G1: 当期市值 | H1: PB | I1: 分红 | J1: 净资产增长率 | K1: 股息率 | L1: 资产收益 | M1: 扣非利润 | N1: 资产收益率 | O1: 归母利润 | P1: 扣非PE | Q1: 营业收入 | R1: 营业成本 | S1: 营业利润 | T1: 净利润 | U1: 归母利润 | V1: 归母/净利润 | W1: 扣非利润 | X1: 销售费用 | Y1: 管理费用 | Z1: 研发费用 | AA1: 融资成本 | AB1: 货币资金 | AC1: 应收 | AD1: 库存 | AE1: 投资 | AF1: 应付 | AG1: 合同负债变动（%） | AH1: 短期贷款 | AI1: 长期贷款 | AJ1: 总资产 | AK1: 净资产 | AL1: 非流动资产 | AM1: 流动负债 | AN1: 总资产-流动负债 | AO1: 经营现金流净额 | AP1: 资本开支 | AS1: 三年平均资本开支 | AT1: 三年经营现金流净额 | AW1: 三年净利润 | AZ1: 现金流/利润 | BA1: 平均现金流 | BB1: 平均自由现金流 | BC1: 净现金 | BD1: 净现金/资本开支 | BE1: 净现金/市值
A2: 港元/人民币汇率 | B2: =[1]正常估值!B2 -> 0.9152
A3: 腾讯控股 | B3: 2023年报 | C3: 304 | D3: =C3*$B$2 -> 278.2208 | E3: 93.42 | F3: 85.27 | G3: =D3*E3 -> 25991.387 | H3: =C3/F3 -> 3.565146 | I3: 3.4 | J3: 0.03 | K3: =I3/C3 -> 0.011184211 | L3: =I3+F3*J3 -> 5.9581 | M3: =W3/E3 -> 16.880754 | N3: =L3/F3 -> 0.069873343 | O3: =U3/E3 -> 12.331407 | P3: =D3*E3/W3 -> 16.481539 | Q3: 6090 | R3: 3159 | S3: 1517 | T3: 1180 | U3: 1152 | V3: =U3/T3 -> 0.97627119 | W3: 1577 | X3: 342 | Y3: 1035 | Z3: 641 | AA3: 127 | AB3: =3621+208 -> 3829 | AC3: 466 | AD3: 4.6 | AE3: 6893 | AF3: 1152 | AH3: 477 | AI3: 3094 | AJ3: 15800 | AK3: 8737 | AL3: 10600 | AM3: 3522 | AN3: =AJ3-AM3 -> 12278 | AO3: 2220 | AP3: 474 | AQ3: 509 | AR3: 622 | AS3: =AVERAGE(AP3:AR3) -> 535 | AT3: 1752 | AU3: 1461 | AV3: 2220 | AW3: 2248 | AX3: 1882 | AY3: 1152 | AZ3: =(AT3+AU3+AV3)/(AW3+AX3+AY3) -> 1.0285877 | BA3: =AVERAGE(AT3:AV3) -> 1811 | BB3: =BA3-AS3 -> 1276 | BC3: =AB3+AE3-AH3-AI3 -> 7151 | BD3: =BC3/AS3 -> 13.366355 | BE3: =BC3/G3 -> 0.2751296 | BF3: =A3 -> 腾讯控股
A4: 腾讯控股 | B4: 2024年报 | C4: 600 | D4: 667 | E4: 91.79 | F4: 105.5 | G4: =D4*E4 -> 61223.93 | H4: =C4/F4 -> 5.6872038 | I4: 4.5 | J4: =F4/F3-1 -> 0.23724639 | K4: =I4/C4 -> 0.0075 | L4: =I4+F4*J4 -> 29.529495 | M4: =W4/E4 -> 24.261902 | N4: =L4/F4 -> 0.27990042 | O4: =U4/E4 -> 21.1352 | P4: =D4*E4/W4 -> 27.491661 | Q4: 6603 | R4: 3110 | S4: 2035 | T4: 1965 | U4: 1940 | V4: =U4/T4 -> 0.98727735 | W4: 2227 | X4: 364 | Y4: 1148 | Z4: 707 | AA4: 120 | AB4: 4760 | AC4: 482 | AD4: 4.4 | AE4: =6534+3389 -> 9923 | AF4: 1273 | AH4: 947 | AI4: 2910 | AJ4: 17800 | AK4: 10500 | AL4: 12800 | AM4: 3969 | AN4: =AJ4-AM4 -> 13831 | AO4: 2585 | AP4: 960 | AQ4: 474 | AR4: 509 | AS4: =AVERAGE(AP4:AR4) -> 647.66667 | AT4: 1461 | AU4: 2220 | AV4: 2585 | AW4: 1882 | AX4: 1152 | AY4: 1941 | AZ4: =(AT4+AU4+AV4)/(AW4+AX4+AY4) -> 1.2594975 | BA4: 2850 | BB4: =BA4-AS4 -> 2202.3333 | BC4: =AB4+AE4-AH4-AI4 -> 10826 | BD4: =BC4/AS4 -> 16.715389 | BE4: =BC4/G4 -> 0.17682628 | BF4: =A4 -> 腾讯控股
A5: 阿里巴巴 | B5: 2024年报 | C5: 80 | D5: =C5*$B$2 -> 73.216 | E5: 193.45 | F5: 48.21 | G5: =D5*E5 -> 14163.635 | H5: =C5/F5 -> 1.6594068 | I5: =(0.125+0.0825)*7.8 -> 1.6185 | J5: 0.05 | K5: =I5/C5 -> 0.02023125 | L5: =I5+F5*J5 -> 4.029 | M5: =W5/E5 -> 4.1199276 | N5: =L5/F5 -> 0.083571873 | O5: =U5/E5 -> 4.1199276 | P5: =D5*E5/W5 -> 17.771186 | Q5: 9411 | R5: 5863 | S5: 1016 | T5: 713 | U5: 797 | V5: =U5/T5 -> 1.1178121 | W5: 797 | X5: 1151 | Y5: 636 | Z5: 523 | AA5: 79 | AB5: =2864+3229 -> 6093 | AC5: 306.86 | AD5: 0 | AE5: 4240 | AF5: 0 | AH5: 290 | AI5: 1418 | AJ5: 17600 | AK5: 11000 | AL5: 10100 | AM5: 4215 | AN5: =AJ5-AM5 -> 13385 | AO5: 1826 | AP5: 330 | AQ5: 533 | AR5: 432 | AS5: =AVERAGE(AP5:AR5) -> 431.66667 | AT5: 1826 | AU5: 1997 | AV5: 1428 | AW5: 713 | AX5: 656 | AY5: 471 | AZ5: =(AT5+AU5+AV5)/(AW5+AX5+AY5) -> 2.8538043 | BA5: =AVERAGE(AT5:AV5) -> 1750.3333 | BB5: =BA5-AS5 -> 1318.6667 | BC5: =AB5+AE5-AH5-AI5 -> 8625 | BD5: =BC5/AS5 -> 19.980695 | BE5: =BC5/G5 -> 0.60895384 | BF5: =A5 -> 阿里巴巴
A6: 阿里巴巴 | B6: 三季报 | C6: 153 | D6: =C6*$B$2 -> 140.0256 | E6: 190.9 | F6: 57.87 | G6: =D6*E6 -> 26730.887 | H6: =C6/F6 -> 2.6438569 | I6: 1.64 | J6: =F6/F5-1 -> 0.20037337 | K6: =I6/C6 -> 0.010718954 | L6: =I6+F6*J6 -> 13.235607 | M6: =W6/E6 -> 6.7836564 | N6: =L6/F6 -> 0.22871275 | O6: =U6/E6 -> 6.7836564 | P6: =D6*E6/W6 -> 20.641612 | Q6: 9963 | R6: 5983 | S6: 1555 | T6: 1260 | U6: 1295 | V6: =U6/T6 -> 1.0277778 | W6: 1295 | X6: 1440 | Y6: 506 | Z6: 572 | AA6: 96 | AB6: =1893+2826 -> 4719 | AC6: 500 | AD6: 0 | AE6: 5670 | AF6: 0 | AH6: 226 | AI6: 2081 | AJ6: 18000 | AK6: 10800 | AL6: 11300 | AM6: 4353 | AN6: =AJ6-AM6 -> 13647 | AO6: 1635 | AP6: 860 | AQ6: 330 | AR6: 533 | AS6: =AVERAGE(AP6:AR6) -> 574.33333 | AT6: 1635 | AU6: 1826 | AV6: 1997 | AW6: 1260 | AX6: 713 | AY6: 656 | AZ6: =(AT6+AU6+AV6)/(AW6+AX6+AY6) -> 2.0760746 | BA6: =AVERAGE(AT6:AV6) -> 1819.3333 | BB6: =BA6-AS6 -> 1245 | BC6: =AB6+AE6-AH6-AI6 -> 8082 | BD6: =BC6/AS6 -> 14.071967 | BE6: =BC6/G6 -> 0.30234687 | BF6: =A6 -> 阿里巴巴
A7: 联想集团 | B7: 2024年报 | C7: 7 | D7: =C7*$B$2 -> 6.4064 | E7: 124.05 | F7: =0.41*7.1 -> 2.911 | G7: =D7*E7 -> 794.71392 | H7: =C7/F7 -> 2.4046719 | I7: 0.385 | J7: 0 | K7: =I7/C7 -> 0.055 | L7: =I7+F7*J7 -> 0.385 | M7: =W7/E7 -> 0.081499395 | N7: =L7/F7 -> 0.13225696 | O7: =U7/E7 -> 0.081499395 | P7: =D7*E7/W7/7.3 -> 10.768044 | Q7: 568 | R7: 471 | S7: 13.9 | T7: 11 | U7: 10.11 | V7: =U7/T7 -> 0.91909091 | W7: 10.11 | X7: 33 | Y7: 24.9 | Z7: 20.28 | AA7: 7.73 | AB7: 37 | AC7: 81.5 | AD7: 67 | AE7: 17.68 | AF7: 105 | AH7: 0.5 | AI7: 35.7 | AJ7: 387 | AK7: 60.8 | AL7: 163 | AM7: 261 | AN7: =AJ7-AM7 -> 126 | AO7: 20.11 | AP7: 7.3 | AQ7: 11.2 | AR7: 10 | AS7: =AVERAGE(AP7:AR7) -> 9.5 | AT7: 20 | AU7: 28 | AV7: 41 | AW7: 11 | AX7: 16.8 | AY7: 21.5 | AZ7: =(AT7+AU7+AV7)/(AW7+AX7+AY7) -> 1.8052738 | BA7: =AVERAGE(AT7:AV7) -> 29.666667 | BB7: =BA7-AS7 -> 20.166667 | BC7: =AB7+AE7-AH7-AI7 -> 18.48 | BD7: =BC7/AS7 -> 1.9452632 | BE7: =BC7/G7 -> 0.023253651 | BF7: =A7 -> 联想集团
A8: 联想集团 | B8: 2025年报 | C8: 9.8 | D8: =C8*$B$2 -> 8.96896 | E8: 124.05 | F8: 3.96 | G8: =D8*E8 -> 1112.5995 | H8: =C8/F8 -> 2.4747475 | I8: 0.385 | J8: 0.0966 | K8: =I8/C8 -> 0.039285714 | L8: =I8+F8*J8 -> 0.767536 | M8: 1.03 | N8: =L8/F8 -> 0.19382222 | O8: =U8/E8*[1]正常估值!D2 -> 0.79356027 | P8: =G8/W8/[1]正常估值!D2 -> 11.302179 | Q8: 691 | R8: 580 | S8: 15.01 | T8: 14.62 | U8: 13.84 | V8: =U8/T8 -> 0.94664843 | W8: 13.84 | X8: 35.85 | Y8: 28.23 | Z8: 22.88 | AA8: 7.63 | AB8: 49 | AC8: 105.07 | AD8: 79 | AE8: 18.25 | AF8: 120 | AH8: 10.3 | AI8: 43.38 | AJ8: 442 | AK8: 66.6 | AL8: 161 | AM8: 300 | AN8: =AJ8-AM8 -> 142 | AO8: 11 | AP8: 6.66 | AQ8: 7.3 | AR8: 11.2 | AS8: =AVERAGE(AP8:AR8) -> 8.3866667 | AT8: 11 | AU8: 20 | AV8: 28 | AW8: 14.62 | AX8: 11 | AY8: 16.8 | AZ8: =(AT8+AU8+AV8)/(AW8+AX8+AY8) -> 1.3908534 | BA8: =AVERAGE(AT8:AV8) -> 19.666667 | BB8: =BA8-AS8 -> 11.28 | BC8: =AB8+AE8-AH8-AI8 -> 13.57 | BD8: =BC8/AS8 -> 1.6180445 | BE8: =BC8/G8 -> 0.012196662 | BF8: =A8 -> 联想集团
A9: 小米集团 | B9: 2023年报 | C9: 15 | D9: =C9*$B$2 -> 13.728 | E9: 249.55 | F9: 6.54 | G9: =D9*E9 -> 3425.8224 | H9: =C9/F9 -> 2.293578 | I9: 0 | J9: 0.09 | K9: =I9/C9 -> 0 | L9: =I9+F9*J9 -> 0.5886 | M9: =W9/E9 -> 0.70126227 | N9: =L9/F9 -> 0.09 | O9: =U9/E9 -> 0.70126227 | P9: =D9*E9/W9 -> 19.576128 | Q9: 2710 | R9: 2135 | S9: 220 | T9: 175 | U9: 175 | V9: =U9/T9 -> 1 | W9: 175 | X9: 192 | Y9: 51 | Z9: 191 | AA9: 15.56 | AB9: =912+213 -> 1125 | AC9: 123 | AD9: 444 | AE9: 675 | AF9: 621 | AH9: 62 | AI9: 217 | AJ9: 3243 | AK9: 1643 | AL9: 1252 | AM9: 1156 | AN9: =AJ9-AM9 -> 2087 | AO9: 413 | AP9: 63 | AQ9: 58 | AR9: 72 | AS9: =AVERAGE(AP9:AR9) -> 64.333333 | AT9: 98 | AU9: -44 | AV9: 413 | AW9: 193 | AX9: 25 | AY9: 175 | AZ9: =(AT9+AU9+AV9)/(AW9+AX9+AY9) -> 1.1882952 | BA9: =AVERAGE(AT9:AV9) -> 155.66667 | BB9: =BA9-AS9 -> 91.333333 | BC9: =AB9+AE9-AH9-AI9 -> 1521 | BD9: =BC9/AS9 -> 23.642487 | BE9: =BC9/G9 -> 0.44398098 | BF9: =A9 -> 小米集团
A10: 小米集团 | B10: 2024年报 | C10: 38 | D10: =C10*$B$2 -> 34.7776 | E10: 251.12 | F10: 7.52 | G10: =D10*E10 -> 8733.3509 | H10: =C10/F10 -> 5.0531915 | I10: 0 | J10: =F10/F9-1 -> 0.14984709 | K10: =I10/C10 -> 0 | L10: =I10+F10*J10 -> 1.1268502 | M10: =W10/E10 -> 0.9437719 | N10: =L10/F10 -> 0.14984709 | O10: =U10/E10 -> 0.9437719 | P10: =D10*E10/W10 -> 36.849582 | Q10: 3659 | R10: 2893 | S10: 279 | T10: 236 | U10: 237 | V10: =U10/T10 -> 1.0042373 | W10: 237 | X10: 254 | Y10: 56 | Z10: 241 | AA10: 2.12 | AB10: 1060 | AC10: 158 | AD10: 625 | AE10: 715 | AF10: 983 | AH10: 133 | AI10: 173 | AJ10: 4031 | AK10: 1892 | AL10: 1774 | AM10: 1754 | AN10: =AJ10-AM10 -> 2277 | AO10: 393 | AP10: 73 | AQ10: 63 | AR10: 58 | AS10: =AVERAGE(AP10:AR10) -> 64.666667 | AT10: 98 | AU10: -44 | AV10: 413 | AW10: 193 | AX10: 25 | AY10: 175 | AZ10: =(AT10+AU10+AV10)/(AW10+AX10+AY10) -> 1.1882952 | BA10: 400 | BB10: =BA10-AS10 -> 335.33333 | BC10: =AB10+AE10-AH10-AI10 -> 1469 | BD10: =BC10/AS10 -> 22.716495 | BE10: =BC10/G10 -> 0.16820577 | BF10: =A10 -> 小米集团
A11: 联邦制药 | B11: 2023年报 | C11: 8.6 | D11: =C11*$B$2 -> 7.87072 | E11: 18.17 | F11: 7.01 | G11: =D11*E11 -> 143.01098 | H11: =C11/F11 -> 1.2268188 | I11: 0.4 | J11: 0.17 | K11: =I11/C11 -> 0.046511628 | L11: =I11+F11*J11 -> 1.5917 | M11: =W11/E11 -> 1.4859659 | N11: =L11/F11 -> 0.22706134 | O11: =U11/E11 -> 1.4859659 | P11: =D11*E11/W11 -> 5.2967031 | Q11: 137 | R11: 74 | S11: 33.5 | T11: 27 | U11: 27 | V11: =U11/T11 -> 1 | W11: 27 | X11: 15.94 | Y11: 7.9 | Z11: 8.08 | AA11: 0.7 | AB11: 52.34 | AC11: 59 | AD11: 22 | AE11: 0.1 | AF11: 42 | AH11: 2 | AI11: 13 | AJ11: 210 | AK11: 127.5 | AL11: 72.3 | AM11: 66 | AN11: =AJ11-AM11 -> 144 | AO11: 24.39 | AP11: 8.2 | AQ11: 4.9 | AR11: 5.3 | AS11: =AVERAGE(AP11:AR11) -> 6.1333333 | AT11: 15.43 | AU11: 20.3 | AV11: 24.4 | AW11: 9.88 | AX11: 15.81 | AY11: 27 | AZ11: =(AT11+AU11+AV11)/(AW11+AX11+AY11) -> 1.1412033 | BA11: =AVERAGE(AT11:AV11) -> 20.043333 | BB11: =BA11-AS11 -> 13.91 | BC11: =AB11+AE11-AH11-AI11 -> 37.44 | BD11: =BC11/AS11 -> 6.1043478 | BE11: =BC11/G11 -> 0.26179808 | BF11: =A11 -> 联邦制药
A12: 联邦制药 | B12: 2024年报 | C12: 12.8 | D12: =C12*$B$2 -> 11.71456 | E12: 18.17 | F12: 7.92 | G12: =D12*E12 -> 212.85356 | H12: =C12/F12 -> 1.6161616 | I12: 0.56 | J12: =F12/F11-1 -> 0.12981455 | K12: =I12/C12 -> 0.04375 | L12: =I12+F12*J12 -> 1.5881312 | M12: =W12/E12 -> 1.4859659 | N12: =L12/F12 -> 0.20052162 | O12: =U12/E12 -> 1.4859659 | P12: =D12*E12/W12 -> 7.883465 | Q12: 137 | R12: 77 | S12: 33 | T12: 27 | U12: 27 | V12: =U12/T12 -> 1 | W12: 27 | X12: 14 | Y12: 8.9 | Z12: 9.86 | AA12: 0.3 | AB12: 74 | AC12: 57 | AD12: 24 | AE12: 0.1 | AF12: 42 | AH12: 8.35 | AI12: 23 | AJ12: 258 | AK12: 144 | AL12: 97.6 | AM12: 88 | AN12: =AJ12-AM12 -> 170 | AO12: 38 | AP12: 14.62 | AQ12: 8.2 | AR12: 4.9 | AS12: =AVERAGE(AP12:AR12) -> 9.24 | AT12: 15.43 | AU12: 20.3 | AV12: 24.4 | AW12: 9.88 | AX12: 15.81 | AY12: 27 | AZ12: =(AT12+AU12+AV12)/(AW12+AX12+AY12) -> 1.1412033 | BA12: =AVERAGE(AT12:AV12) -> 20.043333 | BB12: =BA12-AS12 -> 10.803333 | BC12: =AB12+AE12-AH12-AI12 -> 42.75 | BD12: =BC12/AS12 -> 4.6266234 | BE12: =BC12/G12 -> 0.20084231 | BF12: =A12 -> 联邦制药
A13: 中国海油 | B13: 2023年报 | C13: 16.96 | D13: =C13*$B$2 -> 15.521792 | E13: 475.67 | F13: 14.01 | G13: =D13*E13 -> 7383.2508 | H13: =C13/F13 -> 1.2105639 | I13: =0.66+0.6 -> 1.26 | J13: 0.14 | K13: =I13/C13 -> 0.074292453 | L13: =I13+F13*J13 -> 3.2214 | M13: =W13/E13 -> 2.6320769 | N13: =L13/F13 -> 0.22993576 | O13: =U13/E13 -> 2.6026447 | P13: =D13*E13/W13 -> 5.8971652 | Q13: 4166 | R13: 1078 | S13: 1710 | T13: 1241 | U13: 1238 | V13: =U13/T13 -> 0.99758259 | W13: 1252 | X13: 35 | Y13: 70 | Z13: 16 | AA13: 54 | AB13: 1948 | AC13: 370 | AD13: 65 | AE13: 646 | AF13: 614 | AH13: 241 | AI13: 961 | AJ13: 10100 | AK13: 6679 | AL13: 7553 | AM13: 1239 | AN13: =AJ13-AM13 -> 8861 | AO13: 2097 | AP13: 1209 | AQ13: 947 | AR13: 731 | AS13: =AVERAGE(AP13:AR13) -> 962.33333 | AT13: 1479 | AU13: 2056 | AV13: 2097 | AW13: 703 | AX13: 1417 | AY13: 1238 | AZ13: =(AT13+AU13+AV13)/(AW13+AX13+AY13) -> 1.6771888 | BA13: =AVERAGE(AT13:AV13) -> 1877.3333 | BB13: =BA13-AS13 -> 915 | BC13: =AB13+AE13-AH13-AI13 -> 1392 | BD13: =BC13/AS13 -> 1.4464842 | BE13: =BC13/G13 -> 0.18853484 | BF13: =A13 -> 中国海油
A14: 中国海油 | B14: 2024年报 | C14: 21 | D14: =C14*$B$2 -> 19.2192 | E14: 475.3 | F14: 15.73 | G14: =D14*E14 -> 9134.8858 | H14: =C14/F14 -> 1.3350286 | I14: 1.4 | J14: =F14/F13-1 -> 0.12276945 | K14: =I14/C14 -> 0.066666667 | L14: =I14+F14*J14 -> 3.3311635 | M14: =W14/E14 -> 3.078056 | N14: =L14/F14 -> 0.21177136 | O14: =U14/E14 -> 2.9013255 | P14: =D14*E14/W14 -> 6.2439411 | Q14: 4205 | R14: 786 | S14: 1881 | T14: 1380 | U14: 1379 | V14: =U14/T14 -> 0.99927536 | W14: 1463 | X14: 35 | Y14: 70 | Z14: 16 | AA14: 61 | AB14: =1542+458 -> 2000 | AC14: 337 | AD14: 181 | AE14: 570 | AF14: 597 | AH14: 224 | AI14: 695 | AJ14: 10600 | AK14: 7494 | AL14: 7917 | AM14: 1189 | AN14: =AJ14-AM14 -> 9411 | AO14: 2209 | AP14: 1234 | AQ14: 1209 | AR14: 947 | AS14: =AVERAGE(AP14:AR14) -> 1130 | AT14: 2056 | AU14: 2097 | AV14: 2209 | AW14: 1417 | AX14: 1238 | AY14: 1380 | AZ14: =(AT14+AU14+AV14)/(AW14+AX14+AY14) -> 1.5767038 | BA14: =AVERAGE(AT14:AV14) -> 2120.6667 | BB14: =BA14-AS14 -> 990.66667 | BC14: =AB14+AE14-AH14-AI14 -> 1651 | BD14: =BC14/AS14 -> 1.4610619 | BE14: =BC14/G14 -> 0.1807357 | BF14: =A14 -> 中国海油
A15: 中国移动 | B15: 2023年报 | C15: 62 | D15: =C15*$B$2 -> 56.7424 | E15: 214.14 | F15: 62.72 | G15: =D15*E15 -> 12150.818 | H15: =C15/F15 -> 0.98852041 | I15: 4.8 | J15: 0.03 | K15: =I15/C15 -> 0.077419355 | L15: =I15+F15*J15 -> 6.6816 | M15: =W15/E15 -> 5.5104137 | N15: =L15/F15 -> 0.10653061 | O15: =U15/E15 -> 6.1501821 | P15: =D15*E15/W15 -> 10.297303 | Q15: 10100 | R15: 4117 | S15: 1616 | T15: 1319 | U15: 1317 | V15: =U15/T15 -> 0.9984837 | W15: 1180 | X15: 525 | Y15: 560 | Z15: 287 | AA15: 37 | AB15: =1788+1560 -> 3348 | AC15: 561 | AD15: 120 | AE15: =1817+5+1856 -> 3678 | AF15: 3240 | AH15: 0 | AI15: 0 | AJ15: 19600 | AK15: 13100 | AL15: 14900 | AM15: 5586 | AN15: =AJ15-AM15 -> 14014 | AO15: 3037 | AP15: 1812 | AQ15: 1896 | AR15: 2027 | AS15: =AVERAGE(AP15:AR15) -> 1911.6667 | AT15: 3147 | AU15: 2807 | AV15: 3037 | AW15: 1160 | AX15: 1255 | AY15: 1318 | AZ15: =(AT15+AU15+AV15)/(AW15+AX15+AY15) -> 2.4085186 | BA15: =AVERAGE(AT15:AV15) -> 2997 | BB15: =BA15-AS15 -> 1085.3333 | BC15: =AB15+AE15-AH15-AI15 -> 7026 | BD15: =BC15/AS15 -> 3.6753269 | BE15: =BC15/G15 -> 0.5782327 | BF15: =A15 -> 中国移动
A16: 中国移动 | B16: 2024年报 | C16: 80 | D16: =C16*$B$2 -> 73.216 | E16: 215.27 | F16: 64.69 | G16: =D16*E16 -> 15761.208 | H16: =C16/F16 -> 1.2366672 | I16: =2.49+2.6 -> 5.09 | J16: =F16/F15-1 -> 0.031409439 | K16: =I16/C16 -> 0.063625 | L16: =I16+F16*J16 -> 7.1218766 | M16: =W16/E16 -> 5.6998188 | N16: =L16/F16 -> 0.11009239 | O16: =U16/E16 -> 6.4291355 | P16: =D16*E16/W16 -> 12.845321 | Q16: 10400 | R16: 4325 | S16: 1505 | T16: 1385 | U16: 1384 | V16: =U16/T16 -> 0.99927798 | W16: 1227 | X16: 546 | Y16: 569 | Z16: 281 | AA16: 33 | AB16: =2423+1532 -> 3955 | AC16: 768 | AD16: 112 | AE16: =1986+31+2094 -> 4111 | AF16: 3952 | AH16: 0 | AI16: 0 | AJ16: 20700 | AK16: 13600 | AL16: 15400 | AM16: 6330 | AN16: =AJ16-AM16 -> 14370 | AO16: 3157 | AP16: 1560 | AQ16: 1812 | AR16: 1896 | AS16: =AVERAGE(AP16:AR16) -> 1756 | AT16: 2807 | AU16: 3037 | AV16: 3157 | AW16: 1255 | AX16: 1318 | AY16: 1384 | AZ16: =(AT16+AU16+AV16)/(AW16+AX16+AY16) -> 2.2747031 | BA16: =AVERAGE(AT16:AV16) -> 3000.3333 | BB16: =BA16-AS16 -> 1244.3333 | BC16: =AB16+AE16-AH16-AI16 -> 8066 | BD16: =BC16/AS16 -> 4.5933941 | BE16: =BC16/G16 -> 0.51176279 | BF16: =A16 -> 中国移动
A17: 中国电信 | B17: 2023年报 | C17: 3.81 | D17: =C17*$B$2 -> 3.486912 | E17: 915.07 | F17: 4.84 | G17: =D17*E17 -> 3190.7686 | H17: =C17/F17 -> 0.78719008 | I17: 0.2332 | J17: 0.025 | K17: =I17/D17 -> 0.066878659 | L17: =I17+F17*J17 -> 0.3542 | M17: =W17/E17 -> 0.31363721 | N17: =L17/F17 -> 0.073181818 | O17: =U17/E17 -> 0.33221502 | P17: =D17*E17/W17 -> 11.117661 | Q17: 5135 | R17: 0 | S17: 371 | T17: 304 | U17: 304 | V17: =U17/T17 -> 1 | W17: 287 | X17: 668 | Y17: 357 | Z17: 131 | AA17: 25.45 | AB17: 918.5 | AC17: 322 | AD17: 34 | AE17: 432 | AF17: 1459 | AH17: 28 | AI17: 51 | AJ17: 8358 | AK17: 4472 | AL17: 6628 | AM17: 3108 | AN17: =AJ17-AM17 -> 5250 | AO17: 1386 | AP17: 902 | AQ17: 915 | AR17: 852 | AS17: =AVERAGE(AP17:AR17) -> 889.66667 | AT17: 1375 | AU17: 1364 | AV17: 1375 | AW17: 259 | AX17: 276 | AY17: 304 | AZ17: =(AT17+AU17+AV17)/(AW17+AX17+AY17) -> 4.9034565 | BA17: =AVERAGE(AT17:AV17) -> 1371.3333 | BB17: =BA17-AS17 -> 481.66667 | BC17: =AB17+AE17-AH17-AI17 -> 1271.5 | BD17: =BC17/AS17 -> 1.429187 | BE17: =BC17/G17 -> 0.39849333 | BF17: =A17 -> 中国电信
A18: 中国电信 | B18: 2024年报 | C18: 6.25 | D18: =C18*$B$2 -> 5.72 | E18: 915.07 | F18: 4.94 | G18: =D18*E18 -> 5234.2004 | H18: =C18/F18 -> 1.2651822 | I18: 0.2598 | J18: =F18/F17-1 -> 0.020661157 | K18: =I18/D18 -> 0.04541958 | L18: =I18+F18*J18 -> 0.36186612 | M18: =W18/E18 -> 0.33549346 | N18: =L18/F18 -> 0.07325225 | O18: =U18/E18 -> 0.36062815 | P18: =D18*E18/W18 -> 17.049513 | Q18: 5294 | R18: 0 | S18: 420 | T18: 330 | U18: 330 | V18: =U18/T18 -> 1 | W18: 307 | X18: 667 | Y18: 371 | Z18: 145 | AA18: 24 | AB18: 1020 | AC18: 429 | AD18: 32 | AE18: 442 | AF18: 1605 | AH18: 28 | AI18: 75 | AJ18: 8666 | AK18: 4565 | AL18: 6628 | AM18: 3108 | AN18: =AJ18-AM18 -> 5558 | AO18: 1452 | AP18: 903 | AQ18: 902 | AR18: 915 | AS18: =AVERAGE(AP18:AR18) -> 906.66667 | AT18: 1372 | AU18: 1386 | AV18: 1452 | AW18: 276 | AX18: 304 | AY18: 330 | AZ18: =(AT18+AU18+AV18)/(AW18+AX18+AY18) -> 4.6263736 | BA18: =AVERAGE(AT18:AV18) -> 1403.3333 | BB18: =BA18-AS18 -> 496.66667 | BC18: =AB18+AE18-AH18-AI18 -> 1359 | BD18: =BC18/AS18 -> 1.4988971 | BE18: =BC18/G18 -> 0.25963851 | BF18: =A18 -> 中国电信
A19: 中国联通 | B19: 2023年报 | C19: 5.26 | D19: =C19*$B$2 -> 4.813952 | E19: 305.98 | F19: 12.62 | G19: =D19*E19 -> 1472.973 | H19: =C19/F19 -> 0.41679873 | I19: 0.3366 | J19: 0.025 | K19: =I19/D19 -> 0.069921761 | L19: =I19+F19*J19 -> 0.6521 | M19: =W19/E19 -> 0.61115106 | N19: =L19/F19 -> 0.051671949 | O19: =U19/E19 -> 0.61115106 | P19: =D19*E19/W19 -> 7.8768611 | Q19: 3726 | R19: 347 | S19: 186 | T19: 189 | U19: 187 | V19: =U19/T19 -> 0.98941799 | W19: 187 | X19: 600 | Y19: 1590 | Z19: 0 | AA19: 20 | AB19: =588+244 -> 832 | AC19: 387 | AD19: 22 | AE19: 596 | AF19: 1676 | AH19: 137 | AI19: 319 | AJ19: 6610 | AK19: 3539 | AL19: 5048 | AM19: 2603 | AN19: =AJ19-AM19 -> 4007 | AO19: 1005 | AP19: 793 | AQ19: 725 | AR19: 720 | AS19: =AVERAGE(AP19:AR19) -> 746 | AT19: 1106 | AU19: 1005 | AV19: 1023 | AW19: 144 | AX19: 167 | AY19: 187 | AZ19: =(AT19+AU19+AV19)/(AW19+AX19+AY19) -> 6.2931727 | BA19: =AVERAGE(AT19:AV19) -> 1044.6667 | BB19: =BA19-AS19 -> 298.66667 | BC19: =AB19+AE19-AH19-AI19 -> 972 | BD19: =BC19/AS19 -> 1.3029491 | BE19: =BC19/G19 -> 0.65988988 | BF19: =A19 -> 中国联通
A20: 中国联通 | B20: 2024年报 | C20: 10.2 | D20: =C20*$B$2 -> 9.33504 | E20: 305.98 | F20: 13.1 | G20: =D20*E20 -> 2856.3355 | H20: =C20/F20 -> 0.77862595 | I20: 0.411 | J20: =F20/F19-1 -> 0.038034865 | K20: =I20/D20 -> 0.044027664 | L20: =I20+F20*J20 -> 0.90925674 | M20: =W20/E20 -> 0.67324662 | N20: =L20/F20 -> 0.069408911 | O20: =U20/E20 -> 0.67324662 | P20: =D20*E20/W20 -> 13.865707 | Q20: 3896 | R20: 425 | S20: 212 | T20: 207 | U20: 206 | V20: =U20/T20 -> 0.99516908 | W20: 206 | X20: 643 | Y20: 1595 | Z20: 0 | AA20: 17.8 | AB20: 638 | AC20: 537 | AD20: 25 | AE20: 612 | AF20: 1687 | AH20: 144 | AI20: 254 | AJ20: 6712 | AK20: 3635 | AL20: 5140 | AM20: 2659 | AN20: =AJ20-AM20 -> 4053 | AO20: 1005 | AP20: 793 | AQ20: 725 | AR20: 720 | AS20: =AVERAGE(AP20:AR20) -> 746 | AT20: 1106 | AU20: 1005 | AV20: 1023 | AW20: 144 | AX20: 167 | AY20: 187 | AZ20: =(AT20+AU20+AV20)/(AW20+AX20+AY20) -> 6.2931727 | BA20: =AVERAGE(AT20:AV20) -> 1044.6667 | BB20: =BA20-AS20 -> 298.66667 | BC20: =AB20+AE20-AH20-AI20 -> 852 | BD20: =BC20/AS20 -> 1.1420912 | BE20: =BC20/G20 -> 0.29828428 | BF20: =A20 -> 中国联通
A21: 快手 | B21: 2023年报 | C21: 50 | D21: =C21*$B$2 -> 45.76 | E21: 43.39 | F21: 11.29 | G21: =D21*E21 -> 1985.5264 | H21: =C21/F21 -> 4.428698 | I21: 0 | J21: 0.03 | K21: =I21/C21 -> 0 | L21: =I21+F21*J21 -> 0.3387 | M21: =W21/E21 -> 1.4749942 | N21: =L21/F21 -> 0.03 | O21: =U21/E21 -> 1.4749942 | P21: =D21*E21/W21 -> 31.02385 | Q21: 1135 | R21: 561 | S21: 69 | T21: 64 | U21: 64 | V21: =U21/T21 -> 1 | W21: 64 | X21: 365 | Y21: 35 | Z21: 123 | AA21: 5.77 | AB21: 490 | AC21: 65 | AD21: 0 | AE21: 57 | AF21: 236 | AH21: 33 | AI21: 84 | AJ21: 1063 | AK21: 490 | AL21: 459 | AM21: 488 | AN21: =AJ21-AM21 -> 575 | AO21: 208 | AP21: 49 | AQ21: 46 | AR21: 78 | AS21: =AVERAGE(AP21:AR21) -> 57.666667 | AT21: -55 | AU21: 8 | AV21: 208 | AW21: -780 | AX21: -137 | AY21: 64 | AZ21: =(AT21+AU21+AV21)/(AW21+AX21+AY21) -> -0.1887456 | BA21: =AVERAGE(AT21:AV21) -> 53.666667 | BB21: =BA21-AS21 -> -4 | BC21: =AB21+AE21-AH21-AI21 -> 430 | BD21: =BC21/AS21 -> 7.4566474 | BE21: =BC21/G21 -> 0.21656725 | BF21: =A21 -> 快手
A22: 快手 | B22: 2024年报 | C22: 64 | D22: =C22*$B$2 -> 58.5728 | E22: 43.04 | F22: 14.44 | G22: =D22*E22 -> 2520.9733 | H22: =C22/F22 -> 4.432133 | I22: 0 | J22: =F22/F21-1 -> 0.27900797 | K22: =I22/C22 -> 0 | L22: =I22+F22*J22 -> 4.0288751 | M22: =W22/E22 -> 3.5548327 | N22: =L22/F22 -> 0.27900797 | O22: =U22/E22 -> 3.5548327 | P22: =D22*E22/W22 -> 16.47695 | Q22: 1269 | R22: 576 | S22: 154 | T22: 153 | U22: 153 | V22: =U22/T22 -> 1 | W22: 153 | X22: 411 | Y22: 30 | Z22: 122 | AA22: 8.35 | AB22: =243+273 -> 516 | AC22: 67 | AD22: 0 | AE22: 247 | AF22: 275 | AH22: 37 | AI22: 179 | AJ22: 1399 | AK22: 620 | AL22: 770 | AM22: 598 | AN22: =AJ22-AM22 -> 801 | AO22: 298 | AP22: 81 | AQ22: 49 | AR22: 46 | AS22: =AVERAGE(AP22:AR22) -> 58.666667 | AT22: 8 | AU22: 208 | AV22: 299 | AW22: -137 | AX22: 64 | AY22: 153 | AZ22: =(AT22+AU22+AV22)/(AW22+AX22+AY22) -> 6.4375 | BA22: =AVERAGE(AT22:AV22) -> 171.66667 | BB22: =BA22-AS22 -> 113 | BC22: =AB22+AE22-AH22-AI22 -> 547 | BD22: =BC22/AS22 -> 9.3238636 | BE22: =BC22/G22 -> 0.21697969 | BF22: =A22 -> 快手
A23: 美团 | B23: 2023年报 | C23: 91.4 | D23: =C23*$B$2 -> 83.64928 | E23: 62.35 | F23: 24.34 | G23: =D23*E23 -> 5215.5326 | H23: =C23/F23 -> 3.7551356 | I23: 0 | J23: 0.1 | K23: =I23/C23 -> 0 | L23: =I23+F23*J23 -> 2.434 | M23: =W23/E23 -> 2.2293504 | N23: =L23/F23 -> 0.1 | O23: =U23/E23 -> 2.2293504 | P23: =D23*E23/W23 -> 37.521817 | Q23: 2767 | R23: 1796 | S23: 128 | T23: 139 | U23: 139 | V23: =U23/T23 -> 1 | W23: 139 | X23: 586 | Y23: 94 | Z23: 212 | AA23: 14.25 | AB23: =527+1118 -> 1645 | AC23: 27 | AD23: 13 | AE23: 476 | AF23: 230 | AH23: 218 | AI23: 388 | AJ23: 2930 | AK23: 1520 | AL23: 1099 | AM23: 1009 | AN23: =AJ23-AM23 -> 1921 | AO23: 405 | AP23: 69 | AQ23: 57 | AR23: 90 | AS23: =AVERAGE(AP23:AR23) -> 72 | AT23: -40 | AU23: 114 | AV23: 405 | AW23: -235 | AX23: -67 | AY23: 138 | AZ23: =(AT23+AU23+AV23)/(AW23+AX23+AY23) -> -2.9207317 | BA23: =AVERAGE(AT23:AV23) -> 159.66667 | BB23: =BA23-AS23 -> 87.666667 | BC23: =AB23+AE23-AH23-AI23 -> 1515 | BD23: =BC23/AS23 -> 21.041667 | BE23: =BC23/G23 -> 0.29047848 | BF23: =A23 -> 美团
A24: 美团 | B24: 2024年报 | C24: 104 | D24: =C24*$B$2 -> 95.1808 | E24: 61.11 | F24: 33 | G24: =D24*E24 -> 5816.4987 | H24: =C24/F24 -> 3.1515152 | I24: 0 | J24: 0.17 | K24: =I24/C24 -> 0 | L24: =I24+F24*J24 -> 5.61 | M24: =W24/E24 -> 5.8582883 | N24: =L24/F24 -> 0.17 | O24: =U24/E24 -> 5.8582883 | P24: =D24*E24/W24 -> 16.247203 | Q24: 3376 | R24: 2078 | S24: 368 | T24: 358 | U24: 358 | V24: =U24/T24 -> 1 | W24: 358 | X24: 640 | Y24: 109 | Z24: 210 | AA24: 13.37 | AB24: 1890 | AC24: 31 | AD24: 25 | AE24: 434 | AF24: 456 | AH24: 28 | AI24: 318 | AJ24: 3301 | AK24: 1842 | AL24: 1128 | AM24: 1124 | AN24: =AJ24-AM24 -> 2177 | AO24: 571 | AP24: 110 | AQ24: 69 | AR24: 57 | AS24: =AVERAGE(AP24:AR24) -> 78.666667 | AT24: 114 | AU24: 405 | AV24: 571 | AW24: 358 | AX24: 138 | AY24: -67 | AZ24: =(AT24+AU24+AV24)/(AW24+AX24+AY24) -> 2.5407925 | BA24: =AVERAGE(AT24:AV24) -> 363.33333 | BB24: =BA24-AS24 -> 284.66667 | BC24: =AB24+AE24-AH24-AI24 -> 1978 | BD24: =BC24/AS24 -> 25.144068 | BE24: =BC24/G24 -> 0.34006713 | BF24: =A24 -> 美团
A25: 携程 | B25: 2024年报 | C25: 547 | D25: =C25*$B$2 -> 500.6144 | E25: 6.54 | F25: 247.7 | G25: =D25*E25 -> 3274.0182 | H25: =C25/F25 -> 2.2083165 | I25: 2.333 | J25: 0.15 | K25: =I25/C25 -> 0.0042650823 | L25: =I25+F25*J25 -> 39.488 | M25: =W25/E25 -> 26.146789 | N25: =L25/F25 -> 0.15941865 | O25: =U25/E25 -> 26.146789 | P25: =D25*E25/W25 -> 19.146305 | Q25: 534 | R25: 101 | S25: 170 | T25: 172 | U25: 171 | V25: =U25/T25 -> 0.99418605 | W25: 171 | X25: 119 | Y25: 41 | Z25: 131 | AA25: 17.4 | AB25: 796 | AC25: 125 | AD25: 0 | AE25: 472 | AF25: 166 | AH25: 194 | AI25: 207 | AJ25: 2426 | AK25: 1435 | AL25: 1305 | AM25: 740 | AN25: =AJ25-AM25 -> 1686 | AO25: 196 | AP25: 6 | AQ25: 6 | AR25: 5 | AS25: =AVERAGE(AP25:AR25) -> 5.6666667 | AT25: 26 | AU25: 220 | AV25: 196 | AW25: 172 | AX25: 100 | AY25: 14 | AZ25: =(AT25+AU25+AV25)/(AW25+AX25+AY25) -> 1.5454545 | BA25: =AVERAGE(AT25:AV25) -> 147.33333 | BB25: =BA25-AS25 -> 141.66667 | BC25: =AB25+AE25-AH25-AI25 -> 867 | BD25: =BC25/AS25 -> 153 | BE25: =BC25/G25 -> 0.26481221 | BF25: =A25 -> 携程
A26: 百度 | B26: 2023年报 | C26: 100 | D26: =C26*$B$2 -> 91.52 | E26: 29.03 | F26: 83.94 | G26: =D26*E26 -> 2656.8256 | H26: =C26/F26 -> 1.1913271 | I26: 0 | J26: 0.05 | K26: =I26/C26 -> 0 | L26: =I26+F26*J26 -> 4.197 | M26: =W26/E26 -> 6.2004823 | N26: =L26/F26 -> 0.05 | O26: =U26/E26 -> 6.9927661 | P26: =D26*E26/W26 -> 14.760142 | Q26: 1346 | R26: 650 | S26: 290 | T26: 215 | U26: 203 | V26: =U26/T26 -> 0.94418605 | W26: 180 | X26: 0 | Y26: 0 | Z26: 242 | AA26: 32 | AB26: =347+1687 -> 2034 | AC26: 108 | AE26: 726 | AF26: 60 | AH26: 191 | AI26: 624 | AJ26: 4068 | AK26: 2531 | AL26: 1765 | AM26: 765 | AN26: =AJ26-AM26 -> 3303 | AO26: 366 | AP26: 112 | AQ26: 83 | AR26: 109 | AS26: =AVERAGE(AP26:AR26) -> 101.33333 | AT26: 201 | AU26: 262 | AV26: 366 | AW26: 215 | AX26: 75 | AY26: 76 | AZ26: =(AT26+AU26+AV26)/(AW26+AX26+AY26) -> 2.2650273 | BA26: =AVERAGE(AT26:AV26) -> 276.33333 | BB26: =BA26-AS26 -> 175 | BC26: =AB26+AE26-AH26-AI26 -> 1945 | BD26: =BC26/AS26 -> 19.194079 | BE26: =BC26/G26 -> 0.73207666 | BF26: =A26 -> 百度
A27: 百度 | B27: 2024年报 | C27: 117 | D27: =C27*$B$2 -> 107.0784 | E27: 27.5 | F27: 109.68 | G27: =D27*E27 -> 2944.656 | H27: =C27/F27 -> 1.0667396 | I27: 0 | J27: 0.1365 | K27: =I27/C27 -> 0 | L27: =I27+F27*J27 -> 14.97132 | M27: =W27/E27 -> 7.6363636 | N27: =L27/F27 -> 0.1365 | O27: =U27/E27 -> 8.6181818 | P27: =D27*E27/W27 -> 14.022171 | Q27: 1331 | R27: 661 | S27: 293 | T27: 242 | U27: 237 | V27: =U27/T27 -> 0.97933884 | W27: 210 | X27: 0 | Y27: 0 | Z27: 221 | AA27: 28 | AB27: 1242 | AC27: 116 | AD27: 0 | AE27: 1552 | AF27: 47 | AH27: 270 | AI27: 137 | AJ27: 4505 | AK27: 2852 | AL27: 2934 | AM27: 851 | AN27: =AJ27-AM27 -> 3654 | AO27: 212 | AP27: 86 | AQ27: 112 | AR27: 83 | AS27: =AVERAGE(AP27:AR27) -> 93.666667 | AT27: 212 | AU27: 366 | AV27: 262 | AW27: 242 | AX27: 215 | AY27: 75 | AZ27: =(AT27+AU27+AV27)/(AW27+AX27+AY27) -> 1.5789474 | BA27: =AVERAGE(AT27:AV27) -> 280 | BB27: =BA27-AS27 -> 186.33333 | BC27: =AB27+AE27-AH27-AI27 -> 2387 | BD27: =BC27/AS27 -> 25.483986 | BE27: =BC27/G27 -> 0.810621 | BF27: =A27 -> 百度
A28: 拼多多 | B28: 2024年报 | D28: =120*[1]正常估值!D2 -> 853.536 | E28: =G28/D28 -> 14.210667 | F28: =35.85*[1]正常估值!D2 -> 254.99388 | G28: =1705.28*[1]正常估值!D2 -> 12129.316 | H28: =D28/F28 -> 3.3472803 | I28: 0 | J28: 0.5 | K28: =I28/D28 -> 0 | L28: =I28+F28*J28 -> 127.49694 | M28: =W28/E28 -> 79.095515 | N28: =L28/F28 -> 0.5 | O28: =U28/E28 -> 79.095515 | P28: =D28*E28/W28 -> 10.791206 | Q28: 3938 | R28: 1539 | S28: 1084 | T28: 1124 | U28: 1124 | V28: =U28/T28 -> 1 | W28: 1124 | X28: 1189 | Y28: 0 | Z28: 127 | AA28: 0 | AB28: 3316 | AC28: 37 | AD28: 0 | AE28: 0 | AF28: 0 | AH28: 53 | AI28: 0 | AJ28: 5050 | AK28: 3133 | AL28: 894 | AM28: 1884 | AN28: =AJ28-AM28 -> 3166 | AO28: 1219 | AP28: 10 | AQ28: 6 | AR28: 6 | AS28: =AVERAGE(AP28:AR28) -> 7.3333333 | AT28: 485 | AU28: 941 | AV28: 1219 | AW28: 1124 | AX28: 600 | AY28: 315 | AZ28: =(AT28+AU28+AV28)/(AW28+AX28+AY28) -> 1.2972045 | BA28: =AVERAGE(AT28:AV28) -> 881.66667 | BB28: =BA28-AS28 -> 874.33333 | BC28: =AB28+AE28-AH28-AI28 -> 3263 | BD28: =BC28/AS28 -> 444.95455 | BE28: =BC28/G28 -> 0.26901765 | BF28: =A28 -> 拼多多
A29: 华润啤酒 | B29: 2023年报 | C29: 23.8 | D29: =C29*$B$2 -> 21.78176 | E29: 32.44 | F29: 10.25 | G29: =D29*E29 -> 706.60029 | H29: =C29/F29 -> 2.3219512 | I29: =(0.349+0.287)/B2 -> 0.69493007 | J29: 0.1 | K29: =I29/C29 -> 0.029198742 | L29: =I29+F29*J29 -> 1.7199301 | M29: =W29/E29 -> 1.6029593 | N29: =L29/F29 -> 0.16779806 | O29: =U29/E29 -> 1.6029593 | P29: =D29*E29/W29 -> 13.588467 | Q29: 389 | R29: 228 | S29: 71 | T29: 52 | U29: 52 | V29: =U29/T29 -> 1 | W29: 52 | X29: 81 | Y29: 34 | Z29: 0 | AA29: 2.44 | AB29: 55 | AE29: 52 | AH29: 10 | AI29: 43 | AJ29: 715 | AK29: 342 | AL29: 537 | AM29: 261 | AN29: =AJ29-AM29 -> 454 | AO29: 42 | AP29: 25 | AQ29: 17 | AR29: 15 | AS29: =AVERAGE(AP29:AR29) -> 19 | AT29: 50 | AU29: 68 | AV29: 42 | AW29: 46 | AX29: 43 | AY29: 52 | AZ29: =(AT29+AU29+AV29)/(AW29+AX29+AY29) -> 1.1347518 | BA29: =AVERAGE(AT29:AV29) -> 53.333333 | BB29: =BA29-AS29 -> 34.333333 | BC29: =AB29+AE29-AH29-AI29 -> 54 | BD29: =BC29/AS29 -> 2.8421053 | BE29: =BC29/G29 -> 0.076422272 | BF29: =A29 -> 华润啤酒
A30: 青岛啤酒 | B30: 2023年报 | C30: 50 | D30: =C30*$B$2 -> 45.76 | E30: 13.64 | F30: 20.8 | G30: =D30*E30 -> 624.1664 | H30: =C30/F30 -> 2.4038462 | I30: =2/B2 -> 2.1853147 | J30: 0.09 | K30: =I30/C30 -> 0.043706294 | L30: =I30+F30*J30 -> 4.0573147 | M30: =W30/E30 -> 2.71261 | N30: =L30/F30 -> 0.19506321 | O30: =U30/E30 -> 3.1304985 | P30: =D30*E30/W30 -> 16.869362 | Q30: 339 | R30: 232 | S30: 55 | T30: 43.5 | U30: 42.7 | V30: =U30/T30 -> 0.9816092 | W30: 37 | X30: 47 | Y30: 15.2 | Z30: 1 | AA30: 0.5 | AB30: 213 | AC30: 1 | AD30: 35 | AE30: 3.7 | AF30: 31.5 | AH30: 0 | AI30: 0.6 | AJ30: 493 | AK30: 283 | AL30: 196 | AM30: 169 | AN30: =AJ30-AM30 -> 324 | AO30: 28 | AP30: 16.2 | AQ30: 17.8 | AR30: 16.4 | AS30: =AVERAGE(AP30:AR30) -> 16.8 | AT30: 60 | AU30: 49 | AV30: 28 | AW30: 32 | AX30: 37 | AY30: 43 | AZ30: =(AT30+AU30+AV30)/(AW30+AX30+AY30) -> 1.2232143 | BA30: =AVERAGE(AT30:AV30) -> 45.666667 | BB30: =BA30-AS30 -> 28.866667 | BC30: =AB30+AE30-AH30-AI30 -> 216.1 | BD30: =BC30/AS30 -> 12.863095 | BE30: =BC30/G30 -> 0.34622178 | BF30: =A30 -> 青岛啤酒
A31: 青岛啤酒 | B31: 2024年报 | C31: 53 | D31: =C31*$B$2 -> 48.5056 | E31: 13.64 | F31: 21.3 | G31: =D31*E31 -> 661.61638 | H31: =C31/F31 -> 2.4882629 | I31: 2.113 | J31: =F31/F30-1 -> 0.024038462 | K31: =I31/C31 -> 0.039867925 | L31: =I31+F31*J31 -> 2.6250192 | M31: =W31/E31 -> 3.1891496 | N31: =L31/F31 -> 0.12324034 | O31: =U31/E31 -> 3.1891496 | P31: =D31*E31/W31 -> 15.209572 | Q31: 321 | R31: 215 | S31: 58 | T31: 44.9 | U31: 43.5 | V31: =U31/T31 -> 0.9688196 | W31: 43.5 | X31: 46 | Y31: 14 | Z31: 1 | AA31: 0.5 | AB31: 200 | AC31: 1 | AD31: 36 | AE31: 3.9 | AF31: 32.7 | AH31: 0 | AI31: 0.7 | AJ31: 514 | AK31: 299 | AL31: 262 | AM31: 175 | AN31: =AJ31-AM31 -> 339 | AO31: 28 | AP31: 21.4 | AQ31: 16.2 | AR31: 17.8 | AS31: =AVERAGE(AP31:AR31) -> 18.466667 | AT31: 60 | AU31: 49 | AV31: 28 | AW31: 32 | AX31: 37 | AY31: 43 | AZ31: =(AT31+AU31+AV31)/(AW31+AX31+AY31) -> 1.2232143 | BA31: =AVERAGE(AT31:AV31) -> 45.666667 | BB31: =BA31-AS31 -> 27.2 | BC31: =AB31+AE31-AH31-AI31 -> 203.2 | BD31: =BC31/AS31 -> 11.00361 | BE31: =BC31/G31 -> 0.30712661 | BF31: =A31 -> 青岛啤酒
A32: 百威亚太 | B32: 2024年报 | C32: 8.4 | D32: =C32*$B$2 -> 7.68768 | E32: 132.43 | F32: =6.1*B2 -> 5.58272 | G32: =D32*E32 -> 1018.0795 | H32: =C32/F32 -> 1.5046429 | I32: 0.444 | J32: -0.05 | K32: =I32/C32 -> 0.052857143 | L32: =I32+F32*J32 -> 0.164864 | M32: =W32/E32 -> 0.054821415 | N32: =L32/F32 -> 0.029531125 | O32: =U32/E32 -> 0.054821415 | P32: =D32*E32/W32 -> 140.23133 | Q32: 62.5 | R32: 31 | S32: 10.86 | T32: 7.5 | U32: 7.26 | V32: =U32/T32 -> 0.968 | W32: 7.26 | X32: 16.25 | Y32: 4.77 | Z32: 0 | AA32: 0.35 | AB32: 29.44 | AC32: 3.6 | AD32: 3.76 | AE32: 5.04 | AF32: 16.33 | AH32: 1.36 | AI32: 0.7 | AJ32: 147.8 | AK32: 102.4 | AL32: 109.5 | AM32: 39.33 | AN32: =AJ32-AM32 -> 108.47 | AO32: 11.34 | AP32: 3.8 | AQ32: 5 | AR32: 4.94 | AS32: =AVERAGE(AP32:AR32) -> 4.58 | AT32: 15.77 | AU32: 18.11 | AV32: 11.34 | AW32: 7.5 | AX32: 8.8 | AY32: 9.5 | AZ32: =(AT32+AU32+AV32)/(AW32+AX32+AY32) -> 1.7527132 | BA32: =AVERAGE(AT32:AV32) -> 15.073333 | BB32: =BA32-AS32 -> 10.493333 | BC32: =AB32+AE32-AH32-AI32 -> 32.42 | BD32: =BC32/AS32 -> 7.0786026 | BE32: =BC32/G32 -> 0.031844273 | BF32: =A32 -> 百威亚太
A33: 蒙牛乳业 | B33: 2023年报 | C33: 17.12 | D33: =C33*$B$2 -> 15.668224 | E33: 39.35 | F33: 11.26 | G33: =D33*E33 -> 616.54461 | H33: =C33/F33 -> 1.5204263 | I33: 0.489 | J33: 0.1 | K33: =I33/C33 -> 0.028563084 | L33: =I33+F33*J33 -> 1.615 | M33: =W33/E33 -> 1.2198221 | N33: =L33/F33 -> 0.14342806 | O33: =U33/E33 -> 1.2198221 | P33: =D33*E33/W33 -> 12.844679 | Q33: 986 | R33: 620 | S33: 62 | T33: 49 | U33: 48 | V33: =U33/T33 -> 0.97959184 | W33: 48 | X33: 252 | Y33: 47 | Z33: 0 | AA33: 15.7 | AB33: 213 | AC33: 37 | AD33: 61 | AE33: 309 | AF33: 95 | AH33: 98 | AI33: 276 | AJ33: 1152 | AK33: 443 | AL33: 811 | AM33: 326 | AN33: =AJ33-AM33 -> 826 | AO33: 83 | AP33: 39 | AQ33: 49 | AR33: 62 | AS33: =AVERAGE(AP33:AR33) -> 50 | AT33: 75 | AU33: 83 | AV33: 83 | AW33: 50 | AX33: 53 | AY33: 48 | AZ33: =(AT33+AU33+AV33)/(AW33+AX33+AY33) -> 1.5960265 | BA33: =AVERAGE(AT33:AV33) -> 80.333333 | BB33: =BA33-AS33 -> 30.333333 | BC33: =AB33+AE33-AH33-AI33 -> 148 | BD33: =BC33/AS33 -> 2.96 | BE33: =BC33/G33 -> 0.24004751 | BF33: =A33 -> 蒙牛乳业
A34: 蒙牛乳业 | B34: 2024年报 | C34: 14.45 | D34: =C34*$B$2 -> 13.22464 | E34: 39.16 | F34: 10.6 | G34: =D34*E34 -> 517.8769 | H34: =C34/F34 -> 1.3632075 | I34: 0.509 | J34: =F34/F33-1 -> -0.058614565 | K34: =I34/C34 -> 0.035224913 | L34: =I34+F34*J34 -> -0.11231439 | M34: =W34/E34 -> 1.3942799 | N34: =L34/F34 -> -0.010595697 | O34: =U34/E34 -> 0.026813075 | P34: =D34*E34/W34 -> 9.484925 | Q34: 887 | R34: 536 | S34: 16 | T34: 2.25 | U34: 1.05 | V34: =U34/T34 -> 0.46666667 | W34: 54.6 | X34: 231 | Y34: 42 | Z34: 0 | AA34: 14.7 | AB34: 256 | AC34: 33 | AD34: 49 | AE34: 261 | AF34: 86 | AH34: 267 | AI34: 180 | AJ34: 1063 | AK34: 480 | AL34: 705 | AM34: 370 | AN34: =AJ34-AM34 -> 693 | AO34: 83 | AP34: 36 | AQ34: 39 | AR34: 49 | AS34: =AVERAGE(AP34:AR34) -> 41.333333 | AT34: 83 | AU34: 83 | AV34: 83 | AW34: 50 | AX34: 50 | AY34: 53 | AZ34: =(AT34+AU34+AV34)/(AW34+AX34+AY34) -> 1.627451 | BA34: =AVERAGE(AT34:AV34) -> 83 | BB34: =BA34-AS34 -> 41.666667 | BC34: =AB34+AE34-AH34-AI34 -> 70 | BD34: =BC34/AS34 -> 1.6935484 | BE34: =BC34/G34 -> 0.13516726 | BF34: =A34 -> 蒙牛乳业
A35: 长实集团 | B35: 2023年报 | C35: 31.7 | D35: =C35*$B$2 -> 29.01184 | E35: 35.11 | F35: 111 | G35: =D35*E35 -> 1018.6057 | H35: =C35/F35 -> 0.28558559 | I35: =1.62+0.43 -> 2.05 | J35: 0.033 | K35: =I35/C35 -> 0.06466877 | L35: =I35+F35*J35 -> 5.713 | M35: =W35/E35 -> 4.4146967 | N35: =L35/F35 -> 0.051468468 | O35: =U35/E35 -> 5.0128169 | P35: =D35*E35/W35 -> 6.5716497 | Q35: 710 | R35: 97 | S35: 178 | T35: 175 | U35: 176 | V35: =U35/T35 -> 1.0057143 | W35: 155 | X35: 0 | Y35: 250 | Z35: 0 | AA35: 16 | AB35: 425 | AC35: 15.5 | AD35: 1301 | AE35: 984 | AF35: 41.7 | AH35: 178 | AI35: 426 | AJ35: 5088 | AK35: 3994 | AL35: 3264 | AM35: 518 | AN35: =AJ35-AM35 -> 4570 | AO35: 3.78 | AP35: 43 | AQ35: 62 | AR35: 54 | AS35: =AVERAGE(AP35:AR35) -> 53 | AT35: 254 | AU35: 66 | AV35: 4 | AW35: 215 | AX35: 220 | AY35: 176 | AZ35: =(AT35+AU35+AV35)/(AW35+AX35+AY35) -> 0.53027823 | BA35: =AVERAGE(AT35:AV35) -> 108 | BB35: =BA35-AS35 -> 55 | BC35: =AB35+AE35-AH35-AI35 -> 805 | BD35: =BC35/AS35 -> 15.188679 | BE35: =BC35/G35 -> 0.79029599 | BF35: =A35 -> 长实集团
A36: 长实集团 | B36: 2024年报 | C36: 37 | D36: =C36*$B$2 -> 33.8624 | E36: 35 | F36: 113 | G36: =D36*E36 -> 1185.184 | H36: =C36/F36 -> 0.32743363 | I36: 1.74 | J36: =F36/F35-1 -> 0.018018018 | K36: =I36/C36 -> 0.047027027 | L36: =I36+F36*J36 -> 3.776036 | M36: =W36/E36 -> 3.9714286 | N36: =L36/F36 -> 0.033416248 | O36: =U36/E36 -> 3.9714286 | P36: =D36*E36/W36 -> 8.5265036 | Q36: 716 | R36: 88 | S36: 116 | T36: 137 | U36: 139 | V36: =U36/T36 -> 1.0145985 | W36: 139 | X36: 0 | Y36: 261 | Z36: 0 | AA36: 20 | AB36: 361 | AC36: 21 | AD36: 1298 | AE36: 975 | AF36: 37 | AH36: 111 | AI36: 462 | AJ36: 5017 | AK36: 4002 | AL36: 3258 | AM36: 413 | AN36: =AJ36-AM36 -> 4604 | AO36: 3.78 | AP36: 43 | AQ36: 62 | AR36: 54 | AS36: =AVERAGE(AP36:AR36) -> 53 | AT36: 254 | AU36: 66 | AV36: 4 | AW36: 215 | AX36: 220 | AY36: 176 | AZ36: =(AT36+AU36+AV36)/(AW36+AX36+AY36) -> 0.53027823 | BA36: =AVERAGE(AT36:AV36) -> 108 | BB36: =BA36-AS36 -> 55 | BC36: =AB36+AE36-AH36-AI36 -> 763 | BD36: =BC36/AS36 -> 14.396226 | BE36: =BC36/G36 -> 0.64378189 | BF36: =A36 -> 长实集团
A37: 长和 | B37: 2023年报 | C37: 51 | D37: =C37*$B$2 -> 46.6752 | E37: 38.3 | F37: 143.24 | G37: =D37*E37 -> 1787.6602 | H37: =C37/F37 -> 0.3560458 | I37: =1.775+0.756 -> 2.531 | J37: 0.03 | K37: =I37/C37 -> 0.049627451 | L37: =I37+F37*J37 -> 6.8282 | M37: =W37/E37 -> 6.1357702 | N37: =L37/F37 -> 0.047669645 | O37: =U37/E37 -> 6.1357702 | P37: =D37*E37/W37 -> 7.6070645 | Q37: 2756 | R37: 1057 | S37: 150 | T37: 302 | U37: 235 | V37: =U37/T37 -> 0.7781457 | W37: 235 | X37: 0 | Y37: 945 | Z37: 0 | AA37: 122 | AB37: 1273 | AE37: 3157 | AH37: 719 | AI37: 2711 | AJ37: 11600 | AK37: 6705 | AL37: 9203 | AM37: 1310 | AN37: =AJ37-AM37 -> 10290 | AO37: 514 | AP37: 217 | AQ37: 239 | AR37: 270 | AS37: =AVERAGE(AP37:AR37) -> 242 | AT37: 522 | AU37: 567 | AV37: 514 | AW37: 335 | AX37: 367 | AY37: 235 | AZ37: =(AT37+AU37+AV37)/(AW37+AX37+AY37) -> 1.7107791 | BA37: =AVERAGE(AT37:AV37) -> 534.33333 | BB37: =BA37-AS37 -> 292.33333 | BC37: =AB37+AE37-AH37-AI37 -> 1000 | BD37: =BC37/AS37 -> 4.1322314 | BE37: =BC37/G37 -> 0.55939044 | BF37: =A37 -> 长和
A38: 长江基建 | B38: 2023年报 | C38: 53 | D38: =C38*$B$2 -> 48.5056 | E38: 25.2 | F38: 52.86 | G38: =D38*E38 -> 1222.3411 | H38: =C38/F38 -> 1.0026485 | I38: =1.85+0.71 -> 2.56 | J38: 0.03 | K38: =I38/C38 -> 0.048301887 | L38: =I38+F38*J38 -> 4.1458 | M38: =W38/E38 -> 3.1746032 | N38: =L38/F38 -> 0.078429815 | O38: =U38/E38 -> 3.3730159 | P38: =D38*E38/W38 -> 15.279264 | Q38: 386 | S38: 23.2 | T38: 85 | U38: 85 | V38: =U38/T38 -> 1 | W38: 80 | X38: 0 | Y38: 43 | Z38: 0 | AA38: 7.7 | AB38: 136 | AE38: 1456 | AH38: 90 | AI38: 152 | AJ38: 1659 | AK38: 1333 | AL38: 1483 | AM38: 112 | AN38: =AJ38-AM38 -> 1547 | AO38: =38.5+24 -> 62.5 | AP38: 3.2 | AQ38: 4.7 | AR38: 3.6 | AS38: =AVERAGE(AP38:AR38) -> 3.8333333 | AT38: =31+43 -> 74 | AU38: =17+149 -> 166 | AV38: =24+38.5 -> 62.5 | AW38: 79.5 | AX38: 82 | AY38: 85 | AZ38: =(AT38+AU38+AV38)/(AW38+AX38+AY38) -> 1.2271805 | BA38: =AVERAGE(AT38:AV38) -> 100.83333 | BB38: =BA38-AS38 -> 97 | BC38: =AB38+AE38-AH38-AI38 -> 1350 | BD38: =BC38/AS38 -> 352.17391 | BE38: =BC38/G38 -> 1.104438 | BF38: =A38 -> 长江基建
A39: 电能实业 | B39: 2023年报 | C39: 50.7 | D39: =C39*$B$2 -> 46.40064 | E39: 21.31 | F39: 41.65 | G39: =D39*E39 -> 988.79764 | H39: =C39/F39 -> 1.2172869 | I39: =2.04+0.78 -> 2.82 | J39: 0.02 | K39: =I39/C39 -> 0.055621302 | L39: =I39+F39*J39 -> 3.653 | M39: =W39/E39 -> 2.8155795 | N39: =L39/F39 -> 0.087707083 | O39: =U39/E39 -> 2.8155795 | P39: =D39*E39/W39 -> 16.479961 | Q39: 12.92 | S39: 9.88 | T39: 60 | U39: 60 | V39: =U39/T39 -> 1 | W39: 60 | X39: 0 | Y39: 0 | Z39: 0 | AA39: 1.4 | AB39: 42 | AE39: 913 | AH39: 0 | AI39: 31 | AJ39: 957 | AK39: 888 | AL39: 906 | AM39: 41 | AN39: =AJ39-AM39 -> 916 | AO39: =11.4+46 -> 57.4 | AP39: 0 | AQ39: 0 | AR39: 0 | AS39: =AVERAGE(AP39:AR39) -> 0 | AT39: =9.4+59 -> 68.4 | AU39: =7.7+40 -> 47.7 | AV39: =11.4+46 -> 57.4 | AW39: 61 | AX39: 56 | AY39: 60 | AZ39: =(AT39+AU39+AV39)/(AW39+AX39+AY39) -> 0.98022599 | BA39: =AVERAGE(AT39:AV39) -> 57.833333 | BB39: =BA39-AS39 -> 57.833333 | BC39: =AB39+AE39-AH39-AI39 -> 924 | BE39: =BC39/G39 -> 0.93446825 | BF39: =A39 -> 电能实业
A40: 白云山 | B40: 2023年报 | C40: 16.94 | D40: =C40*$B$2 -> 15.503488 | E40: 16.26 | F40: 24.9 | G40: =D40*E40 -> 252.08671 | H40: =C40/F40 -> 0.68032129 | I40: =0.749/B2 -> 0.81840035 | J40: 0.1 | K40: =I40/C40 -> 0.048311709 | L40: =I40+F40*J40 -> 3.3084003 | M40: =W40/E40 -> 2.5215252 | N40: =L40/F40 -> 0.13286748 | O40: =U40/E40 -> 2.5215252 | P40: =D40*E40/W40 -> 6.1484565 | Q40: 755 | R40: 617 | S40: 50 | T40: 43 | U40: 41 | V40: =U40/T40 -> 0.95348837 | W40: 41 | X40: 61 | Y40: 24 | Z40: 7.8 | AA40: 4.7 | AB40: 213 | AC40: 160 | AD40: 115 | AE40: 19 | AF40: 157 | AH40: 78 | AI40: 39 | AJ40: 786 | AK40: 367 | AL40: 226 | AM40: 389 | AN40: =AJ40-AM40 -> 397 | AO40: 41 | AP40: 16 | AQ40: 14 | AR40: 13 | AS40: =AVERAGE(AP40:AR40) -> 14.333333 | AT40: 57 | AU40: 70 | AV40: 41 | AW40: 43 | AX40: 43 | AY40: 37 | AZ40: =(AT40+AU40+AV40)/(AW40+AX40+AY40) -> 1.3658537 | BA40: =AVERAGE(AT40:AV40) -> 56 | BB40: =BA40-AS40 -> 41.666667 | BC40: =AB40+AE40-AH40-AI40 -> 115 | BD40: =BC40/AS40 -> 8.0232558 | BE40: =BC40/G40 -> 0.45619223 | BF40: =A40 -> 白云山
A41: 白云山 | B41: 2024年报 | C41: 18.02 | D41: =C41*$B$2 -> 16.491904 | E41: 16.26 | F41: 25.48 | G41: =D41*E41 -> 268.15836 | H41: =C41/F41 -> 0.70722135 | I41: 0.875 | J41: 0.03 | K41: =I41/C41 -> 0.048557159 | L41: =I41+F41*J41 -> 1.6394 | M41: =W41/E41 -> 1.4489545 | N41: =L41/F41 -> 0.064340659 | O41: =U41/E41 -> 1.7435424 | P41: =D41*E41/W41 -> 11.381934 | Q41: 751 | R41: 630 | S41: 36 | T41: 30 | U41: 28.35 | V41: =U41/T41 -> 0.945 | W41: 23.56 | X41: 56 | Y41: 24 | Z41: 7.64 | AA41: 4.18 | AB41: 183 | AC41: 162 | AD41: 128 | AE41: 16 | AF41: 163 | AH41: 91 | AI41: 28 | AJ41: 817 | AK41: 378 | AL41: 239 | AM41: 389 | AN41: =AJ41-AM41 -> 428 | AO41: 34.4 | AP41: 16 | AQ41: 14 | AR41: 11.3 | AS41: =AVERAGE(AP41:AR41) -> 13.766667 | AT41: 34.4 | AU41: 70 | AV41: 41 | AW41: 30 | AX41: 43 | AY41: 43 | AZ41: =(AT41+AU41+AV41)/(AW41+AX41+AY41) -> 1.2534483 | BA41: =AVERAGE(AT41:AV41) -> 48.466667 | BB41: =BA41-AS41 -> 34.7 | BC41: =AB41+AE41-AH41-AI41 -> 80 | BD41: =BC41/AS41 -> 5.811138 | BE41: =BC41/G41 -> 0.29833118 | BF41: =A41 -> 白云山
A42: 石药集团 | B42: 2023年报 | C42: 5.5 | D42: =C42*$B$2 -> 5.0336 | E42: 118.96 | F42: 2.79 | G42: =D42*E42 -> 598.79706 | H42: =D42/F42 -> 1.8041577 | I42: 0.32 | J42: 0.13 | K42: =I42/D42 -> 0.063572791 | L42: =I42+F42*J42 -> 0.6827 | M42: =W42/E42 -> 0.49596503 | N42: =L42/F42 -> 0.24469534 | O42: =U42/E42 -> 0.49596503 | P42: =D42*E42/W42 -> 10.149103 | Q42: 315 | R42: 93 | S42: 74 | T42: 61 | U42: 59 | V42: =U42/T42 -> 0.96721311 | W42: 59 | X42: 91 | Y42: 12 | Z42: 48 | AA42: 0.3 | AB42: 131 | AC42: 96 | AD42: 31 | AE42: 39 | AF42: 28 | AH42: 6 | AI42: 1 | AJ42: 463 | AK42: 350 | AL42: 195 | AM42: 102 | AN42: =AJ42-AM42 -> 361 | AO42: 42 | AP42: 19 | AQ42: 27 | AR42: 17.6 | AS42: =AVERAGE(AP42:AR42) -> 21.2 | AT42: 42 | AU42: 76 | AV42: 46 | AW42: 61 | AX42: 62 | AY42: 57 | AZ42: =(AT42+AU42+AV42)/(AW42+AX42+AY42) -> 0.91111111 | BA42: =AVERAGE(AT42:AV42) -> 54.666667 | BB42: =BA42-AS42 -> 33.466667 | BC42: =AB42+AE42-AH42-AI42 -> 163 | BD42: =BC42/AS42 -> 7.6886792 | BE42: =BC42/G42 -> 0.27221243 | BF42: =A42 -> 石药集团
A43: 石药集团 | B43: 2024年报 | C43: 7.43 | D43: =C43*$B$2 -> 6.799936 | E43: 115.44 | F43: 2.77 | G43: =D43*E43 -> 784.98461 | H43: =D43/F43 -> 2.4548505 | I43: 0.25 | J43: =F43/F42-1 -> -0.0071684588 | K43: =I43/D43 -> 0.036765052 | L43: =I43+F43*J43 -> 0.23014337 | M43: =W43/E43 -> 0.37248787 | N43: =L43/F43 -> 0.083084249 | O43: =U43/E43 -> 0.37248787 | P43: =D43*E43/W43 -> 18.255456 | Q43: 290 | R43: 87 | S43: 57 | T43: 43 | U43: 43 | V43: =U43/T43 -> 1 | W43: 43 | X43: 87 | Y43: 11 | Z43: 52 | AA43: 0.4 | AB43: 83 | AC43: 92 | AD43: 31 | AE43: 39 | AF43: 26 | AH43: 4.5 | AI43: 0.6 | AJ43: 444 | AK43: 339 | AL43: 225 | AM43: 96 | AN43: =AJ43-AM43 -> 348 | AO43: 42 | AP43: 26.8 | AQ43: 19 | AR43: 27 | AS43: =AVERAGE(AP43:AR43) -> 24.266667 | AT43: 38 | AU43: 42 | AV43: 76 | AW43: 43 | AX43: 61 | AY43: 62 | AZ43: =(AT43+AU43+AV43)/(AW43+AX43+AY43) -> 0.93975904 | BA43: =AVERAGE(AT43:AV43) -> 52 | BB43: =BA43-AS43 -> 27.733333 | BC43: =AB43+AE43-AH43-AI43 -> 116.9 | BD43: =BC43/AS43 -> 4.8173077 | BE43: =BC43/G43 -> 0.14892012 | BF43: =A43 -> 石药集团
A44: 李宁 | B44: 2023年报 | C44: 19.14 | D44: =C44*$B$2 -> 17.516928 | E44: 25.84 | F44: 9.24 | G44: =D44*E44 -> 452.63742 | H44: =C44/F44 -> 2.0714286 | I44: =0.3775+0.1854 -> 0.5629 | J44: 0.075 | K44: =I44/D44 -> 0.03213463 | L44: =I44+F44*J44 -> 1.2559 | M44: =W44/E44 -> 1.2383901 | N44: =L44/F44 -> 0.13591991 | O44: =U44/E44 -> 1.2383901 | P44: =D44*E44/W44 -> 14.144919 | Q44: 276 | R44: 143 | S44: 39 | T44: 32 | U44: 32 | V44: =U44/T44 -> 1 | W44: 32 | X44: 91 | Y44: 13.3 | Z44: 0 | AA44: 1.8 | AB44: 89 | AC44: 12 | AD44: 25 | AE44: 20 | AF44: 18 | AH44: 7.2 | AI44: 18.3 | AJ44: 342 | AK44: 244 | AL44: 206 | AM44: 73 | AN44: =AJ44-AM44 -> 269 | AO44: 47 | AP44: 17.4 | AQ44: 18.2 | AR44: 11.2 | AS44: =AVERAGE(AP44:AR44) -> 15.6 | AT44: 65 | AU44: 39 | AV44: 47 | AW44: 40 | AX44: 41 | AY44: 32 | AZ44: =(AT44+AU44+AV44)/(AW44+AX44+AY44) -> 1.3362832 | BA44: =AVERAGE(AT44:AV44) -> 50.333333 | BB44: =BA44-AS44 -> 34.733333 | BC44: =AB44+AE44-AH44-AI44 -> 83.5 | BD44: =BC44/AS44 -> 5.3525641 | BE44: =BC44/G44 -> 0.18447436 | BF44: =A44 -> 李宁
A45: 李宁 | B45: 2024年报 | C45: 17.5 | D45: =C45*$B$2 -> 16.016 | E45: 25.85 | F45: 9.3 | G45: =D45*E45 -> 414.0136 | H45: =C45/F45 -> 1.8817204 | I45: 0.5848 | J45: =F45/F44-1 -> 0.0064935065 | K45: =I45/D45 -> 0.036513487 | L45: =I45+F45*J45 -> 0.64518961 | M45: =W45/E45 -> 1.237911 | N45: =L45/F45 -> 0.069375227 | O45: =U45/E45 -> 1.1605416 | P45: =D45*E45/W45 -> 12.937925 | Q45: 287 | R45: 145 | S45: 39 | T45: 30 | U45: 30 | V45: =U45/T45 -> 1 | W45: 32 | X45: 92 | Y45: 15.4 | Z45: 0 | AA45: 2.54 | AB45: 158 | AC45: 10 | AD45: 26 | AE45: 22 | AF45: 16 | AH45: 5.5 | AI45: 13.85 | AJ45: 357 | AK45: 261 | AL45: 152 | AM45: 76 | AN45: =AJ45-AM45 -> 281 | AO45: 47 | AP45: 17.4 | AQ45: 18.2 | AR45: 11.2 | AS45: =AVERAGE(AP45:AR45) -> 15.6 | AT45: 65 | AU45: 39 | AV45: 47 | AW45: 40 | AX45: 41 | AY45: 32 | AZ45: =(AT45+AU45+AV45)/(AW45+AX45+AY45) -> 1.3362832 | BA45: =AVERAGE(AT45:AV45) -> 50.333333 | BB45: =BA45-AS45 -> 34.733333 | BC45: =AB45+AE45-AH45-AI45 -> 160.65 | BD45: =BC45/AS45 -> 10.298077 | BE45: =BC45/G45 -> 0.38803073 | BF45: =A45 -> 李宁
A46: 安踏 | B46: 2023年报 | C46: 77 | D46: =C46*$B$2 -> 70.4704 | E46: 28.07 | F46: 18.17 | G46: =D46*E46 -> 1978.1041 | H46: =C46/F46 -> 4.2377545 | I46: 2.33 | J46: =F46/12.68-1 -> 0.4329653 | K46: =I46/D46 -> 0.033063527 | L46: =I46+F46*J46 -> 10.196979 | M46: =W46/E46 -> 3.6337727 | N46: =L46/F46 -> 0.56119865 | O46: =U46/E46 -> 3.6337727 | P46: =D46*E46/W46 -> 19.393178 | Q46: 624 | R46: 233 | S46: 163 | T46: 113 | U46: 102 | V46: =U46/T46 -> 0.90265487 | W46: 102 | X46: 217 | Y46: 37 | Z46: 0 | AA46: 5.5 | AB46: 380 | AC46: 37 | AD46: 72 | AE46: 112 | AF46: 32 | AH46: 67 | AI46: 148 | AJ46: 922 | AK46: 560 | AL46: 401 | AM46: 206 | AN46: =AJ46-AM46 -> 716 | AO46: 196 | AP46: 12 | AQ46: 16 | AR46: 14 | AS46: =AVERAGE(AP46:AR46) -> 14 | AT46: 118 | AU46: 75 | AV46: 75 | AW46: 113 | AX46: 82 | AY46: 82 | AZ46: =(AT46+AU46+AV46)/(AW46+AX46+AY46) -> 0.96750903 | BA46: =AVERAGE(AT46:AV46) -> 89.333333 | BB46: =BA46-AS46 -> 75.333333 | BC46: =AB46+AE46-AH46-AI46 -> 277 | BD46: =BC46/AS46 -> 19.785714 | BE46: =BC46/G46 -> 0.14003307 | BF46: =A46 -> 安踏
A47: 安踏 | B47: 2024年报 | C47: 81 | D47: =C47*$B$2 -> 74.1312 | E47: 28.07 | F47: 21.86 | G47: =D47*E47 -> 2080.8628 | H47: =C47/F47 -> 3.705398 | I47: 2.36 | J47: =F47/F46-1 -> 0.203082 | K47: =I47/D47 -> 0.031835449 | L47: =I47+F47*J47 -> 6.7993726 | M47: =W47/E47 -> 5.5575347 | N47: =L47/F47 -> 0.31104175 | O47: =U47/E47 -> 5.5575347 | P47: =D47*E47/W47 -> 13.338864 | Q47: 708 | R47: 268 | S47: 217 | T47: 170 | U47: 156 | V47: =U47/T47 -> 0.91764706 | W47: 156 | X47: 256 | Y47: 42 | Z47: 0 | AA47: 6.3 | AB47: 340 | AC47: 45 | AD47: 108 | AE47: 178 | AF47: 43 | AH47: 118 | AI47: 164 | AJ47: 1126 | AK47: 667 | AL47: 601 | AM47: 286 | AN47: =AJ47-AM47 -> 840 | AO47: 167 | AP47: 33 | AQ47: 12 | AR47: 16 | AS47: =AVERAGE(AP47:AR47) -> 20.333333 | AT47: 121 | AU47: 118 | AV47: 75 | AW47: 170 | AX47: 113 | AY47: 82 | AZ47: =(AT47+AU47+AV47)/(AW47+AX47+AY47) -> 0.86027397 | BA47: 200 | BB47: 160 | BC47: =AB47+AE47-AH47-AI47 -> 236 | BD47: =BC47/AS47 -> 11.606557 | BE47: =BC47/G47 -> 0.11341449 | BF47: =A47 -> 安踏
A48: 361度 | B48: 2023年报 | C48: 4.38 | D48: =C48*$B$2 -> 4.008576 | E48: 20.68 | F48: 4.39 | G48: =D48*E48 -> 82.897352 | H48: =C48/F48 -> 0.9977221 | I48: =0.165+0.139 -> 0.304 | J48: 0.1 | K48: =I48/C48 -> 0.069406393 | L48: =I48+F48*J48 -> 0.743 | M48: =W48/E48 -> 0.46470019 | N48: =L48/F48 -> 0.16924829 | O48: =U48/E48 -> 0.46470019 | P48: =D48*E48/W48 -> 8.6261552 | Q48: 84 | R48: 50 | S48: 13.65 | T48: 10.4 | U48: 9.61 | V48: =U48/T48 -> 0.92403846 | W48: 9.61 | X48: 18.6 | Y48: 6.44 | Z48: 0 | AA48: 0.2 | AB48: 52 | AC48: 38.3 | AD48: 13.5 | AE48: 0.2 | AF48: 15 | AH48: 0.5 | AI48: 2.46 | AJ48: 131 | AK48: 97 | AL48: 14.5 | AM48: 31 | AN48: =AJ48-AM48 -> 100 | AO48: 4.08 | AP48: 0.6 | AQ48: 0.3 | AR48: 0.1 | AS48: =AVERAGE(AP48:AR48) -> 0.33333333 | AT48: 3.72 | AU48: 3.8 | AV48: 4.08 | AW48: 6 | AX48: 7.47 | AY48: 9.61 | AZ48: =(AT48+AU48+AV48)/(AW48+AX48+AY48) -> 0.50259965 | BA48: =AVERAGE(AT48:AV48) -> 3.8666667 | BB48: =BA48-AS48 -> 3.5333333 | BC48: =AB48+AE48-AH48-AI48 -> 49.24 | BD48: =BC48/AS48 -> 147.72 | BE48: =BC48/G48 -> 0.59398761 | BF48: =A48 -> 361度
A49: 361度 | B49: 2024年报 | C49: 6.05 | D49: =C49*$B$2 -> 5.53696 | E49: 20.68 | F49: 4.53 | G49: =D49*E49 -> 114.50433 | H49: =C49/F49 -> 1.3355408 | I49: 0.265 | J49: =F49/F48-1 -> 0.031890661 | K49: =I49/C49 -> 0.043801653 | L49: =I49+F49*J49 -> 0.40946469 | M49: =W49/E49 -> 0.55560928 | N49: =L49/F49 -> 0.090389557 | O49: =U49/E49 -> 0.55560928 | P49: =D49*E49/W49 -> 9.9655642 | Q49: 101 | R49: 59 | S49: 15.7 | T49: 11.9 | U49: 11.49 | V49: =U49/T49 -> 0.96554622 | W49: 11.49 | X49: 22 | Y49: 7 | Z49: 0 | AA49: 0.1 | AB49: 43 | AC49: 44 | AD49: 21 | AE49: 0.2 | AF49: 13.3 | AH49: 0.5 | AI49: 2.2 | AJ49: 134 | AK49: 98 | AL49: 13.6 | AM49: 34 | AN49: =AJ49-AM49 -> 100 | AO49: 5 | AP49: 2.69 | AQ49: 0.6 | AR49: 0.3 | AS49: =AVERAGE(AP49:AR49) -> 1.1966667 | AT49: 5.24 | AU49: 3.8 | AV49: 5 | AW49: 11.5 | AX49: 9.6 | AY49: 7.5 | AZ49: =(AT49+AU49+AV49)/(AW49+AX49+AY49) -> 0.49090909 | BA49: =AVERAGE(AT49:AV49) -> 4.68 | BB49: =BA49-AS49 -> 3.4833333 | BC49: =AB49+AE49-AH49-AI49 -> 40.5 | BD49: =BC49/AS49 -> 33.844011 | BE49: =BC49/G49 -> 0.35369841 | BF49: =A49 -> 361度
A50: 特步国际 | B50: 2024年报 | C50: 5.47 | D50: =C50*$B$2 -> 5.006144 | E50: 27.75 | F50: 3.36 | G50: =D50*E50 -> 138.9205 | H50: =C50/F50 -> 1.6279762 | I50: =0.095+0.16 -> 0.255 | J50: 0 | K50: =I50/C50 -> 0.046617916 | L50: =I50+F50*J50 -> 0.255 | M50: =W50/E50 -> 0.45189189 | N50: =L50/F50 -> 0.075892857 | O50: =U50/E50 -> 0.37117117 | P50: =D50*E50/W50 -> 11.078189 | Q50: 143 | R50: 83 | S50: 14 | T50: 10.33 | U50: 10.3 | V50: =U50/T50 -> 0.99709584 | W50: =U50+2.24 -> 12.54 | X50: 33.69 | Y50: 15.4 | Z50: 0 | AA50: 1.8 | AB50: 41.6 | AC50: 50 | AD50: 18 | AE50: 7.5 | AF50: 25 | AH50: 20 | AI50: 22.4 | AJ50: 173 | AK50: 89 | AL50: 52.8 | AM50: 59 | AN50: =AJ50-AM50 -> 114 | AO50: 12.55 | AP50: 6.61 | AQ50: 3.89 | AR50: 3.65 | AS50: =AVERAGE(AP50:AR50) -> 4.7166667 | AT50: 7 | AU50: 12.55 | AV50: 5.72 | AW50: 10.3 | AX50: 9.12 | AY50: 8.9 | AZ50: =(AT50+AU50+AV50)/(AW50+AX50+AY50) -> 0.89230226 | BA50: =AVERAGE(AT50:AV50) -> 8.4233333 | BB50: =BA50-AS50 -> 3.7066667 | BC50: =AB50+AE50-AH50-AI50 -> 6.7 | BD50: =BC50/AS50 -> 1.4204947 | BE50: =BC50/G50 -> 0.048229024 | BF50: =A50 -> 特步国际
A51: 特步国际 | B51: 2024年报 | C51: 5.94 | D51: =C51*$B$2 -> 5.436288 | E51: 27.75 | F51: 3.24 | G51: =D51*E51 -> 150.85699 | H51: =C51/F51 -> 1.8333333 | I51: =0.095+0.156 -> 0.251 | J51: =F51/F50-1 -> -0.035714286 | K51: =I51/C51 -> 0.042255892 | L51: =I51+F51*J51 -> 0.13528571 | M51: =W51/E51 -> 0.47027027 | N51: =L51/F51 -> 0.04175485 | O51: =U51/E51 -> 0.44612613 | P51: =D51*E51/W51 -> 11.559923 | Q51: 152 | R51: 85 | S51: 17 | T51: 12.38 | U51: 12.38 | V51: =U51/T51 -> 1 | W51: =U51+0.67 -> 13.05 | X51: 36.62 | Y51: 16 | Z51: 0 | AA51: 1.4 | AB51: 36 | AC51: 50 | AD51: 16 | AE51: 18 | AF51: 22 | AH51: 12.4 | AI51: 18 | AJ51: 160 | AK51: 87 | AL51: 47.4 | AM51: 53 | AN51: =AJ51-AM51 -> 107 | AO51: 12.28 | AP51: 3.17 | AQ51: 3.89 | AR51: 3.65 | AS51: =AVERAGE(AP51:AR51) -> 3.57 | AT51: 12.28 | AU51: 12.55 | AV51: 5.72 | AW51: 12.38 | AX51: 10.3 | AY51: 9.12 | AZ51: =(AT51+AU51+AV51)/(AW51+AX51+AY51) -> 0.96069182 | BA51: =AVERAGE(AT51:AV51) -> 10.183333 | BB51: =BA51-AS51 -> 6.6133333 | BC51: =AB51+AE51-AH51-AI51 -> 23.6 | BD51: =BC51/AS51 -> 6.6106443 | BE51: =BC51/G51 -> 0.15643955 | BF51: =A51 -> 特步国际
A52: 飞鹤 | B52: 2023年报 | C52: 3.37 | D52: =C52*$B$2 -> 3.084224 | E52: 90.67 | F52: 2.64 | G52: =D52*E52 -> 279.64659 | H52: =C52/F52 -> 1.2765152 | I52: =0.1484+0.1349 -> 0.2833 | J52: 0.04 | K52: =I52/C52 -> 0.084065282 | L52: =I52+F52*J52 -> 0.3889 | M52: =W52/E52 -> 0.37498621 | N52: =L52/F52 -> 0.14731061 | O52: =U52/E52 -> 0.37498621 | P52: =D52*E52/W52 -> 8.2248997 | Q52: 195 | R52: 69 | S52: 49 | T52: 33 | U52: 34 | V52: =U52/T52 -> 1.030303 | W52: 34 | X52: 67 | Y52: 17.6 | Z52: 0 | AA52: 0.5 | AB52: 192 | AE52: 1 | AH52: 6 | AI52: 10 | AJ52: 362 | AK52: 263 | AL52: 136 | AM52: 74 | AN52: =AJ52-AM52 -> 288 | AO52: 42 | AP52: 15.2 | AQ52: 24.8 | AR52: 20.2 | AS52: =AVERAGE(AP52:AR52) -> 20.066667 | AT52: 68 | AU52: 63 | AV52: 41 | AW52: 69 | AX52: 49 | AY52: 34 | AZ52: =(AT52+AU52+AV52)/(AW52+AX52+AY52) -> 1.1315789 | BA52: =AVERAGE(AT52:AV52) -> 57.333333 | BB52: =BA52-AS52 -> 37.266667 | BC52: =AB52+AE52-AH52-AI52 -> 177 | BD52: =BC52/AS52 -> 8.820598 | BE52: =BC52/G52 -> 0.63294174 | BF52: =A52 -> 飞鹤
A53: 飞鹤 | B53: 2024年报 | C53: 4.14 | D53: =C53*$B$2 -> 3.788928 | E53: 90.67 | F53: 2.75 | G53: =D53*E53 -> 343.5421 | H53: =C53/F53 -> 1.5054545 | I53: 0.29 | J53: =F53/F52-1 -> 0.041666667 | K53: =I53/C53 -> 0.070048309 | L53: =I53+F53*J53 -> 0.40458333 | M53: =W53/E53 -> 0.37498621 | N53: =L53/F53 -> 0.14712121 | O53: =U53/E53 -> 0.37498621 | P53: =D53*E53/W53 -> 10.104179 | Q53: 195 | R53: 69 | S53: 49 | T53: 33 | U53: 34 | V53: =U53/T53 -> 1.030303 | W53: 34 | X53: 67 | Y53: 17.6 | Z53: 0 | AA53: 0.5 | AB53: 192 | AE53: 1 | AH53: 6 | AI53: 10 | AJ53: 362 | AK53: 263 | AL53: 135 | AM53: 66 | AN53: =AJ53-AM53 -> 296 | AO53: 42 | AP53: 15 | AQ53: 15.2 | AR53: 24.8 | AS53: =AVERAGE(AP53:AR53) -> 18.333333 | AT53: 68 | AU53: 63 | AV53: 41 | AW53: 69 | AX53: 49 | AY53: 34 | AZ53: =(AT53+AU53+AV53)/(AW53+AX53+AY53) -> 1.1315789 | BA53: =AVERAGE(AT53:AV53) -> 57.333333 | BB53: =BA53-AS53 -> 39 | BC53: =AB53+AE53-AH53-AI53 -> 177 | BD53: =BC53/AS53 -> 9.6545455 | BE53: =BC53/G53 -> 0.51522069 | BF53: =A53 -> 飞鹤
A54: 周生生 | B54: 2023年报 | C54: 7.33 | D54: =C54*$B$2 -> 6.708416 | E54: 6.77 | F54: 18.02 | G54: =D54*E54 -> 45.415976 | H54: =C54/F54 -> 0.40677026 | I54: 0.6 | J54: 0.025 | K54: =I54/C54 -> 0.081855389 | L54: =I54+F54*J54 -> 1.0505 | M54: =W54/E54 -> 1.4859675 | N54: =L54/F54 -> 0.058296337 | O54: =U54/E54 -> 1.4963072 | P54: =C54*E54/W54 -> 4.9328131 | Q54: 250 | R54: 184 | S54: 12.97 | T54: 10 | U54: 10.13 | V54: =U54/T54 -> 1.013 | W54: 10.06 | X54: 42.54 | Y54: 9.89 | Z54: 0 | AA54: 1.3 | AB54: 11.1 | AC54: 9.7 | AD54: 122.6 | AE54: 9.21 | AF54: 1.35 | AH54: 16.06 | AI54: 9.71 | AJ54: 192 | AK54: 121.7 | AL54: 37 | AM54: 54 | AN54: =AJ54-AM54 -> 138 | AO54: 21.6 | AP54: 4.43 | AQ54: 3.93 | AR54: 4.16 | AS54: =AVERAGE(AP54:AR54) -> 4.1733333 | AT54: -7.25 | AU54: 0.33 | AV54: 21.6 | AW54: 6.43 | AX54: 4.52 | AY54: 10.13 | AZ54: =(AT54+AU54+AV54)/(AW54+AX54+AY54) -> 0.69639469 | BA54: =AVERAGE(AT54:AV54) -> 4.8933333 | BB54: =BA54-AS54 -> 0.72 | BC54: =AB54+AE54-AH54-AI54 -> -5.46 | BD54: =BC54/AS54 -> -1.3083067 | BE54: =BC54/G54 -> -0.12022201 | BF54: =A54 -> 周生生
A55: 周生生 | B55: 2024年报 | C55: 8.33 | D55: =C55*$B$2 -> 7.623616 | E55: 6.73 | F55: 18.48 | G55: =D55*E55 -> 51.306936 | H55: =C55/F55 -> 0.45075758 | I55: 0.51 | J55: =F55/F54-1 -> 0.025527192 | K55: =I55/C55 -> 0.06122449 | L55: =I55+F55*J55 -> 0.98174251 | M55: =W55/E55 -> 1.1485884 | N55: =L55/F55 -> 0.053124595 | O55: =U55/E55 -> 1.1976226 | P55: =C55*E55/W55 -> 7.2523803 | Q55: 212 | R55: 152 | S55: 10.3 | T55: 7.94 | U55: 8.06 | V55: =U55/T55 -> 1.0151134 | W55: =8.06-0.33 -> 7.73 | X55: 40 | Y55: 9.92 | Z55: 0 | AA55: 1.4 | AB55: 13.57 | AC55: 7.9 | AD55: 127.9 | AE55: 10.1 | AF55: 1.35 | AH55: 17.8 | AI55: 7.9 | AJ55: 196.5 | AK55: 123.8 | AL55: 36 | AM55: 61 | AN55: =AJ55-AM55 -> 135.5 | AO55: =15.4-5.27 -> 10.13 | AP55: 2.14 | AQ55: 4.43 | AR55: 3.93 | AS55: =AVERAGE(AP55:AR55) -> 3.5 | AT55: 0.33 | AU55: 21.6 | AV55: =15.4-5.27 -> 10.13 | AW55: 8.06 | AX55: 10.13 | AY55: 4.52 | AZ55: =(AT55+AU55+AV55)/(AW55+AX55+AY55) -> 1.4117129 | BA55: =AVERAGE(AT55:AV55) -> 10.686667 | BB55: =BA55-AS55 -> 7.1866667 | BC55: =AB55+AE55-AH55-AI55 -> -2.03 | BD55: =BC55/AS55 -> -0.58 | BE55: =BC55/G55 -> -0.039565801 | BF55: =A55 -> 周生生
A56: 六福集团 | B56: 2024中报 | C56: 22.42 | D56: =C56*$B$2 -> 20.518784 | E56: 5.87 | F56: 22.52 | G56: =D56*E56 -> 120.44526 | H56: =C56/F56 -> 0.9955595 | I56: 1.2 | J56: 0.06 | K56: =I56/C56 -> 0.05352364 | L56: =I56+F56*J56 -> 2.5512 | M56: =W56/E56 -> 3.0153322 | N56: =L56/F56 -> 0.11328597 | O56: =U56/E56 -> 3.0153322 | P56: =C56*E56/W56 -> 7.4353333 | Q56: 153 | R56: 112 | S56: 21 | T56: 17.6 | U56: 17.7 | V56: =U56/T56 -> 1.0056818 | W56: 17.7 | X56: 20.4 | Y56: 2.56 | Z56: 0 | AA56: 0.6 | AB56: 19.34 | AC56: 2.2 | AD56: 98.63 | AE56: 0 | AF56: 3.16 | AH56: 17.48 | AI56: 2.94 | AJ56: 171 | AK56: 132 | AL56: 46 | AM56: 35 | AN56: =AJ56-AM56 -> 136 | AO56: 16.6 | AP56: 6.76 | AQ56: 1 | AR56: 1.8 | AS56: =AVERAGE(AP56:AR56) -> 3.1866667 | AT56: 16.63 | AU56: 13.4 | AV56: 7.4 | AW56: 17.67 | AX56: 12.9 | AY56: 13.9 | AZ56: =(AT56+AU56+AV56)/(AW56+AX56+AY56) -> 0.84169103 | BA56: =AVERAGE(AT56:AV56) -> 12.476667 | BB56: =BA56-AS56 -> 9.29 | BC56: =AB56+AE56-AH56-AI56 -> -1.08 | BD56: =BC56/AS56 -> -0.33891213 | BE56: =BC56/G56 -> -0.0089667288 | BF56: =A56 -> 六福集团
A57: 周大福 | B57: 2023年报 | C57: 12.6 | D57: =C57*$B$2 -> 11.53152 | E57: 99.88 | F57: 2.57 | G57: =D57*E57 -> 1151.7682 | H57: =C57/F57 -> 4.9027237 | I57: 0.6 | J57: 0 | K57: =I57/C57 -> 0.047619048 | L57: =I57+F57*J57 -> 0.6 | M57: =W57/E57 -> 0.60072087 | N57: =L57/F57 -> 0.23346304 | O57: =U57/E57 -> 0.65078094 | P57: =C57*E57/W57 -> 20.9748 | Q57: 1087 | R57: 864 | S57: 88 | T57: 66 | U57: 65 | V57: =U57/T57 -> 0.98484848 | W57: 60 | X57: 95 | Y57: 42 | Z57: 0 | AA57: 7.05 | AB57: 77 | AC57: 29 | AD57: 646.5 | AE57: 1.1 | AF57: 10.4 | AH57: 259 | AI57: 40 | AJ57: 888 | AK57: 267 | AL57: 95 | AM57: 581 | AN57: =AJ57-AM57 -> 307 | AO57: 103 | AP57: 5.8 | AQ57: 9.6 | AR57: 19.8 | AS57: =AVERAGE(AP57:AR57) -> 11.733333 | AT57: 139 | AU57: 101 | AV57: 138 | AW57: 67 | AX57: 54 | AY57: 65 | AZ57: =(AT57+AU57+AV57)/(AW57+AX57+AY57) -> 2.0322581 | BA57: =AVERAGE(AT57:AV57) -> 126 | BB57: =BA57-AS57 -> 114.26667 | BC57: =AB57+AE57-AH57-AI57 -> -220.9 | BD57: =BC57/AS57 -> -18.826705 | BE57: =BC57/G57 -> -0.19179206 | BF57: =A57 -> 周大福
A58: 周大生 | B58: 2023年报 | D58: 13.1 | E58: 10.96 | F58: 5.73 | G58: =D58*E58 -> 143.576 | H58: =D58/F58 -> 2.2862129 | I58: 0.95 | J58: 0.05 | K58: =I58/D58 -> 0.072519084 | L58: =I58+F58*J58 -> 1.2365 | M58: =W58/E58 -> 1.1569343 | N58: =L58/F58 -> 0.21579407 | O58: =U58/E58 -> 1.2007299 | P58: =D58*E58/W58 -> 11.323028 | Q58: 163 | R58: 133 | S58: 17 | T58: 13.13 | U58: 13.16 | V58: =U58/T58 -> 1.0022848 | W58: 12.68 | X58: 9.44 | Y58: 1.06 | Z58: 0.1 | AA58: 0.3 | AB58: 8.5 | AC58: 15 | AD58: 36 | AE58: 1.55 | AF58: 1.5 | AH58: 2 | AI58: 0.2 | AJ58: 80 | AK58: 64 | AL58: 17 | AM58: 16 | AN58: =AJ58-AM58 -> 64 | AO58: 1.39 | AP58: 2.15 | AQ58: 1.23 | AR58: 1.54 | AS58: =AVERAGE(AP58:AR58) -> 1.64 | AT58: 1.97 | AU58: 10.18 | AV58: 1.39 | AW58: 12.25 | AX58: 10.91 | AY58: 13.16 | AZ58: =(AT58+AU58+AV58)/(AW58+AX58+AY58) -> 0.37279736 | BA58: =AVERAGE(AT58:AV58) -> 4.5133333 | BB58: =BA58-AS58 -> 2.8733333 | BC58: =AB58+AE58-AH58-AI58 -> 7.85 | BD58: =BC58/AS58 -> 4.7865854 | BE58: =BC58/G58 -> 0.054674876 | BF58: =A58 -> 周大生
A59: 统一企业中国 | B59: 2023年报 | C59: 6.43 | D59: =C59*$B$2 -> 5.884736 | E59: 43.19 | F59: 3.1 | G59: =D59*E59 -> 254.16175 | H59: =C59/F59 -> 2.0741935 | I59: 0.55 | J59: 0 | K59: =I59/C59 -> 0.085536547 | L59: =I59+F59*J59 -> 0.55 | M59: =W59/E59 -> 0.32519102 | N59: =L59/F59 -> 0.17741935 | O59: =U59/E59 -> 0.38666358 | P59: =C59*E59/W59 -> 19.772994 | Q59: 286 | R59: 199 | S59: 22.44 | T59: 16.7 | U59: 16.7 | V59: =U59/T59 -> 1 | W59: =16.67-3.5*0.75 -> 14.045 | X59: 63 | Y59: 10.7 | Z59: 0 | AA59: 0.6 | AB59: 41 | AC59: 5.86 | AD59: 21.26 | AE59: 8.5 | AF59: 21.2 | AH59: 10.2 | AI59: 0.6 | AJ59: 221 | AK59: 134 | AL59: 143 | AM59: 92 | AN59: =AJ59-AM59 -> 129 | AO59: 30.5 | AP59: 9.6 | AQ59: 4.4 | AR59: 3.8 | AS59: =AVERAGE(AP59:AR59) -> 5.9333333 | AT59: 31 | AU59: 14.3 | AV59: 24 | AW59: 15 | AX59: 12 | AY59: 16.7 | AZ59: =(AT59+AU59+AV59)/(AW59+AX59+AY59) -> 1.5858124 | BA59: =AVERAGE(AT59:AV59) -> 23.1 | BB59: =BA59-AS59 -> 17.166667 | BC59: =AB59+AE59-AH59-AI59 -> 38.7 | BD59: =BC59/AS59 -> 6.5224719 | BE59: =BC59/G59 -> 0.15226524 | BF59: =A59 -> 统一企业中国
A60: 统一企业中国 | B60: 2024年报 | C60: 8.3 | D60: =C60*$B$2 -> 7.59616 | E60: 43.19 | F60: 3.1 | G60: =D60*E60 -> 328.07815 | H60: =C60/F60 -> 2.6774194 | I60: 0.4281 | J60: 0 | K60: =I60/C60 -> 0.051578313 | L60: =I60+F60*J60 -> 0.4281 | M60: =W60/E60 -> 0.42833989 | N60: =L60/F60 -> 0.13809677 | O60: =U60/E60 -> 0.42833989 | P60: =C60*E60/W60 -> 19.377135 | Q60: 303 | R60: 205 | S60: 24.3 | T60: 18.5 | U60: 18.5 | V60: =U60/T60 -> 1 | W60: 18.5 | X60: 67 | Y60: 11 | Z60: 0 | AA60: 0.7 | AB60: 51 | AC60: 6.3 | AD60: 25 | AE60: 8.8 | AF60: 22.8 | AH60: 2.3 | AI60: 0.6 | AJ60: 234 | AK60: 134 | AL60: 143 | AM60: 92 | AN60: =AJ60-AM60 -> 142 | AO60: 44 | AP60: 7 | AQ60: 9.6 | AR60: 4.4 | AS60: =AVERAGE(AP60:AR60) -> 7 | AT60: 44 | AU60: 31 | AV60: 14.3 | AW60: 18.5 | AX60: 16.7 | AY60: 12.2 | AZ60: =(AT60+AU60+AV60)/(AW60+AX60+AY60) -> 1.8839662 | BA60: =AVERAGE(AT60:AV60) -> 29.766667 | BB60: =BA60-AS60 -> 22.766667 | BC60: =AB60+AE60-AH60-AI60 -> 56.9 | BD60: =BC60/AS60 -> 8.1285714 | BE60: =BC60/G60 -> 0.17343429 | BF60: =A60 -> 统一企业中国
A61: 康师傅控股 | B61: 2023年报 | C61: 12.16 | D61: =C61*$B$2 -> 11.128832 | E61: 56.34 | F61: 2.47 | G61: =D61*E61 -> 626.99839 | H61: =C61/F61 -> 4.9230769 | I61: 0.594 | J61: 0 | K61: =I61/C61 -> 0.048848684 | L61: =I61+F61*J61 -> 0.594 | M61: =W61/E61 -> 0.55378062 | N61: =L61/F61 -> 0.24048583 | O61: =U61/E61 -> 0.55378062 | P61: =C61*E61/W61 -> 21.958154 | Q61: 804 | R61: 560 | S61: 32 | T61: 35.2 | U61: 31.2 | V61: =U61/T61 -> 0.88636364 | W61: 31.2 | X61: 179 | Y61: 26.2 | Z61: 0 | AA61: 5.2 | AB61: 114 | AC61: 15.8 | AD61: 43.9 | AE61: 12.7 | AF61: 85.7 | AH61: 86 | AI61: 54 | AJ61: 532 | AK61: 172 | AL61: 327 | AM61: 292 | AN61: =AJ61-AM61 -> 240 | AO61: 55 | AP61: 36 | AQ61: 32 | AR61: 30 | AS61: =AVERAGE(AP61:AR61) -> 32.666667 | AT61: 54 | AU61: 45 | AV61: 55 | AW61: 35 | AX61: 31 | AY61: 44 | AZ61: =(AT61+AU61+AV61)/(AW61+AX61+AY61) -> 1.4 | BA61: =AVERAGE(AT61:AV61) -> 51.333333 | BB61: =BA61-AS61 -> 18.666667 | BC61: =AB61+AE61-AH61-AI61 -> -13.3 | BD61: =BC61/AS61 -> -0.40714286 | BE61: =BC61/G61 -> -0.021212176 | BF61: =A61 -> 康师傅控股
A62: 康师傅控股 | B62: 2024年报 | C62: 11.4 | D62: =C62*$B$2 -> 10.43328 | E62: 56.34 | F62: 2.53 | G62: =D62*E62 -> 587.811 | H62: =C62/F62 -> 4.5059289 | I62: =0.3314+0.3314 -> 0.6628 | J62: =F62/F61-1 -> 0.024291498 | K62: =I62/C62 -> 0.058140351 | L62: =I62+F62*J62 -> 0.72425749 | M62: =W62/E62 -> 0.66205183 | N62: =L62/F62 -> 0.28626778 | O62: =U62/E62 -> 0.66205183 | P62: =C62*E62/W62 -> 17.219196 | Q62: 807 | R62: 540 | S62: 63.5 | T62: 43.2 | U62: 37.3 | V62: =U62/T62 -> 0.86342593 | W62: 37.3 | X62: 180 | Y62: 28.3 | Z62: 0 | AA62: 4.2 | AB62: =94+6.7 -> 100.7 | AC62: 16 | AD62: 40 | AE62: 12.4 | AF62: 81 | AH62: 117 | AI62: 17.8 | AJ62: 531 | AK62: 176 | AL62: 352 | AM62: 324 | AN62: =AJ62-AM62 -> 207 | AO62: 82.6 | AP62: 36 | AQ62: 36 | AR62: 32 | AS62: =AVERAGE(AP62:AR62) -> 34.666667 | AT62: 83 | AU62: 55 | AV62: 45 | AW62: 43 | AX62: 35 | AY62: 31 | AZ62: =(AT62+AU62+AV62)/(AW62+AX62+AY62) -> 1.6788991 | BA62: =AVERAGE(AT62:AV62) -> 61 | BB62: =BA62-AS62 -> 26.333333 | BC62: =AB62+AE62-AH62-AI62 -> -21.7 | BD62: =BC62/AS62 -> -0.62596154 | BE62: =BC62/G62 -> -0.036916628 | BF62: =A62 -> 康师傅控股
A63: 百胜中国 | B63: 2023年报 | D63: =333.4/7.8 -> 42.74359 | E63: 3.86 | F63: =118.78/7.8 -> 15.228205 | G63: =D63*E63 -> 164.99026 | H63: =D63/F63 -> 2.8068698 | I63: 0.55 | J63: 0.03 | K63: =I63/D63 -> 0.012867427 | L63: =I63+F63*J63 -> 1.0068462 | M63: =W63/E63 -> 2.142487 | N63: =L63/F63 -> 0.066117191 | O63: =U63/E63 -> 2.142487 | P63: =D63*E63/W63 -> 19.950454 | Q63: 110 | R63: 87 | S63: 12.3 | T63: 9 | U63: 8.27 | V63: =U63/T63 -> 0.91888889 | W63: 8.27 | X63: 0 | Y63: 10.3 | Z63: 0 | AA63: 0 | AB63: 29.3 | AC63: 26 | AD63: 40 | AE63: 12.4 | AF63: 81 | AH63: 117 | AI63: 17.8 | AJ63: 532 | AK63: 71.2 | AL63: 84 | AM63: 23 | AN63: =AJ63-AM63 -> 509 | AO63: 14.73 | AP63: 0 | AQ63: 0 | AR63: 0 | AS63: =AVERAGE(AP63:AR63) -> 0 | AT63: 11.3 | AU63: 14.1 | AV63: 14.7 | AW63: 13.9 | AX63: 6.85 | AY63: 12.3 | AZ63: =(AT63+AU63+AV63)/(AW63+AX63+AY63) -> 1.2133132 | BA63: =AVERAGE(AT63:AV63) -> 13.366667 | BB63: =BA63-AS63 -> 13.366667 | BC63: =AB63+AE63-AH63-AI63 -> -93.1 | BE63: =BC63/G63 -> -0.56427575 | BF63: =A63 -> 百胜中国
A64: 招商局港口 | B64: 2023年报 | C64: 14.4 | D64: =C64*$B$2 -> 13.17888 | E64: 41.98 | F64: =25.01*B2 -> 22.889152 | G64: =D64*E64 -> 553.24938 | H64: =D64/F64 -> 0.57576969 | I64: 0.71 | J64: -0.05 | K64: =I64/C64 -> 0.049305556 | L64: =I64+F64*J64 -> -0.4344576 | M64: =W64/E64 -> 1.5245355 | N64: =L64/F64 -> -0.018980939 | O64: =U64/E64 -> 1.5302525 | P64: =D64*E64/W64 -> 8.6445216 | Q64: 115 | R64: 63.3 | S64: 28.2 | T64: 73.9 | U64: 64.24 | V64: =U64/T64 -> 0.86928281 | W64: 64 | X64: 0 | Y64: 15 | Z64: 0 | AA64: 17.7 | AB64: 157 | AC64: 8.4 | AD64: 1.87 | AE64: 950 | AF64: 3.6 | AH64: 161.5 | AI64: 213 | AJ64: 1723 | AK64: 1208 | AL64: 1529 | AM64: 241 | AN64: =AJ64-AM64 -> 1482 | AO64: 72.4 | AP64: 13 | AQ64: 15 | AR64: 18 | AS64: =AVERAGE(AP64:AR64) -> 15.333333 | AT64: 88 | AU64: 88 | AV64: 72 | AW64: 84 | AX64: 80 | AY64: 64 | AZ64: =(AT64+AU64+AV64)/(AW64+AX64+AY64) -> 1.0877193 | BA64: =AVERAGE(AT64:AV64) -> 82.666667 | BB64: =BA64-AS64 -> 67.333333 | BC64: =AB64+AE64-AH64-AI64 -> 732.5 | BD64: =BC64/AS64 -> 47.771739 | BE64: =BC64/G64 -> 1.3239961 | BF64: =A64 -> 招商局港口
A65: 中远海运港口 | B65: 2023年报 | C65: 4.95 | D65: =C65*$B$2 -> 4.53024 | E65: 36.72 | F65: =12.41*B2 -> 11.357632 | G65: =D65*E65 -> 166.35041 | H65: =D65/F65 -> 0.39887188 | I65: 0.277 | J65: -0.04 | K65: =I65/C65 -> 0.055959596 | L65: =I65+F65*J65 -> -0.17730528 | M65: =W65/E65 -> 0.088507625 | N65: =L65/F65 -> -0.015611113 | O65: =U65/E65 -> 0.088507625 | P65: =D65*E65/W65 -> 51.184742 | Q65: 14.54 | R65: 10.33 | S65: 1.32 | T65: 3.94 | U65: 3.25 | V65: =U65/T65 -> 0.8248731 | W65: 3.25 | X65: 0 | Y65: 1.65 | Z65: 0 | AA65: 1.71 | AB65: 12.1 | AC65: 1.17 | AD65: 0.2 | AE65: 46 | AF65: 0.9 | AH65: 3.9 | AI65: 30.4 | AJ65: 119 | AK65: 68.4 | AL65: 108 | AM65: 11.3 | AN65: =AJ65-AM65 -> 107.7 | AO65: 4.82 | AP65: 3.5 | AQ65: 3.3 | AR65: 3.8 | AS65: =AVERAGE(AP65:AR65) -> 3.5333333 | AT65: 4.1 | AU65: 4.68 | AV65: 4.82 | AW65: 3.55 | AX65: 3.05 | AY65: 3.25 | AZ65: =(AT65+AU65+AV65)/(AW65+AX65+AY65) -> 1.3807107 | BA65: =AVERAGE(AT65:AV65) -> 4.5333333 | BB65: =BA65-AS65 -> 1 | BC65: =AB65+AE65-AH65-AI65 -> 23.8 | BD65: =BC65/AS65 -> 6.7358491 | BE65: =BC65/G65 -> 0.14307148 | BF65: =A65 -> 中远海运港口
A66: 新秀丽 | B66: 2023年报 | C66: 14.62 | D66: =C66*$B$2 -> 13.380224 | E66: 14.22 | F66: 8.08 | G66: =D66*E66 -> 190.26679 | H66: =D66/F66 -> 1.6559683 | I66: 0.82 | J66: 0.33 | K66: =I66/C66 -> 0.056087551 | L66: =I66+F66*J66 -> 3.4864 | M66: =W66/E66 -> 0.29324895 | N66: =L66/F66 -> 0.43148515 | O66: =U66/E66 -> 0.29324895 | P66: =D66*E66/W66 -> 45.627526 | Q66: 36.8 | R66: 15 | S66: 5.85 | T66: 4.5 | U66: 4.17 | V66: =U66/T66 -> 0.92666667 | W66: 4.17 | X66: 12.69 | Y66: 2.5 | Z66: 0 | AA66: 1.73 | AB66: 7.17 | AC66: 3.04 | AD66: 6.96 | AE66: 0 | AF66: 5 | AH66: 2.08 | AI66: 20.88 | AJ66: 51 | AK66: 14.51 | AL66: 33.4 | AM66: 10.9 | AN66: =AJ66-AM66 -> 40.1 | AO66: 5.65 | AP66: 1.1 | AQ66: 1.1 | AR66: 0.6 | AS66: =AVERAGE(AP66:AR66) -> 0.93333333 | AT66: 3.87 | AU66: 2.76 | AV66: 5.34 | AW66: 0.14 | AX66: 3.13 | AY66: 4.17 | AZ66: =(AT66+AU66+AV66)/(AW66+AX66+AY66) -> 1.608871 | BA66: =AVERAGE(AT66:AV66) -> 3.99 | BB66: =BA66-AS66 -> 3.0566667 | BC66: =AB66+AE66-AH66-AI66 -> -15.79 | BD66: =BC66/AS66 -> -16.917857 | BE66: =BC66/G66 -> -0.082988736 | BF66: =A66 -> 新秀丽
A67: 悠然牧业 | B67: 2023年报 | C67: 1.25 | D67: =C67*$B$2 -> 1.144 | E67: 38.93 | F67: 3.27 | G67: =D67*E67 -> 44.53592 | H67: =D67/F67 -> 0.34984709 | I67: 0 | J67: -0.1 | K67: =I67/C67 -> 0 | L67: =I67+F67*J67 -> -0.327 | M67: =W67/E67 -> -0.26971487 | N67: =L67/F67 -> -0.1 | O67: =U67/E67 -> -0.26971487 | P67: =D67*E67/W67 -> -4.2415162 | Q67: 187 | R67: 175 | S67: -12.14 | T67: -14.53 | U67: -10.5 | V67: =U67/T67 -> 0.72264281 | W67: -10.5 | X67: 6.2 | Y67: 7.78 | Z67: 0 | AA67: 10.83 | AB67: 40.7 | AC67: 7.96 | AD67: 45.05 | AE67: 10.7 | AF67: 21.1 | AH67: 166.54 | AI67: 114.28 | AJ67: 462 | AK67: 131 | AL67: 348 | AM67: 209 | AN67: =AJ67-AM67 -> 253 | AO67: 65 | AP67: 29 | AQ67: 87 | AS67: =AVERAGE(AP67:AR67) -> 58 | AT67: 22.66 | AU67: 25.48 | AV67: 43.9 | AW67: 15.6 | AX67: 4.15 | AY67: -10.5 | AZ67: =(AT67+AU67+AV67)/(AW67+AX67+AY67) -> 9.9502703 | BA67: =AVERAGE(AT67:AV67) -> 30.68 | BB67: =BA67-AS67 -> -27.32 | BC67: =AB67+AE67-AH67-AI67 -> -229.42 | BD67: =BC67/AS67 -> -3.9555172 | BE67: =BC67/G67 -> -5.1513475 | BF67: =A67 -> 悠然牧业
A68: 悠然牧业 | B68: 2025中报 | C68: 3 | D68: =C68*$B$2 -> 2.7456 | E68: 38.93 | F68: 3.1 | G68: =D68*E68 -> 106.88621 | H68: =C68/F68 -> 0.96774194 | I68: 0 | J68: -0.07 | K68: =I68/C68 -> 0 | L68: =I68+F68*J68 -> -0.217 | M68: =W68/E68 -> -0.15412278 | N68: =L68/F68 -> -0.07 | O68: =U68/E68 -> -0.15412278 | P68: =D68*E68/W68 -> -17.814368 | Q68: =201*1.023 -> 205.623 | R68: =175*1.04 -> 182 | S68: -3.6 | T68: -5 | U68: -6 | V68: =U68/T68 -> 1.2 | W68: -6 | X68: 6 | Y68: 8 | Z68: 0 | AA68: 8 | AB68: 20.63 | AC68: 7.55 | AD68: 29.5 | AE68: 8.7 | AF68: 12.67 | AH68: 176 | AI68: 92 | AJ68: 423 | AK68: 119 | AL68: 344 | AM68: 202 | AN68: =AJ68-AM68 -> 221 | AO68: 58 | AP68: 17 | AQ68: 29 | AR68: 87 | AS68: =AVERAGE(AP68:AR68) -> 44.333333 | AT68: 44 | AU68: 25.48 | AV68: 58 | AW68: -8.6 | AX68: -14.5 | AY68: 4 | AZ68: =(AT68+AU68+AV68)/(AW68+AX68+AY68) -> -6.6743455 | BA68: =AVERAGE(AT68:AV68) -> 42.493333 | BB68: =BA68-AS68 -> -1.84 | BC68: =AB68+AE68-AH68-AI68 -> -238.67 | BD68: =BC68/AS68 -> -5.3835338 | BE68: =BC68/G68 -> -2.2329354 | BF68: =A68 -> 悠然牧业
A69: 万国数据 | B69: 2024年报 | C69: 33.16 | D69: =C69*$B$2 -> 30.348032 | E69: 15.55 | F69: 17.96 | G69: =D69*E69 -> 471.9119 | H69: =C69/F69 -> 1.8463252 | I69: 0 | J69: 0.1 | K69: =I69/C69 -> 0 | L69: =I69+F69*J69 -> 1.796 | M69: =W69/E69 -> 2.1864952 | N69: =L69/F69 -> 0.1 | O69: =U69/E69 -> 2.1864952 | P69: =D69*E69/W69 -> 13.879762 | Q69: 103 | R69: 81 | S69: 38.6 | T69: 33 | U69: 34 | V69: =U69/T69 -> 1.030303 | W69: 34 | X69: 1.16 | Y69: 9.18 | Z69: 0.4 | AA69: 19.25 | AB69: 79 | AC69: 30 | AD69: 0 | AE69: 75.45 | AF69: 26 | AH69: 51 | AI69: 394 | AJ69: 736 | AK69: 237 | AL69: 620 | AM69: 91 | AN69: =AJ69-AM69 -> 645 | AO69: 19.4 | AS69: 32 | AZ69: 1 | BA69: 20 | BB69: =BA69-AS69 -> -12 | BC69: =AB69+AE69-AH69-AI69 -> -290.55 | BD69: =BC69/AS69 -> -9.0796875 | BE69: =BC69/G69 -> -0.61568696 | BF69: =A69 -> 万国数据
A70: 华晨中国 | B70: 2023年报 | C70: 1.73 | D70: =C70*$B$2 -> 1.583296 | E70: 50.45 | F70: 10.13 | G70: =D70*E70 -> 79.877283 | H70: =D70/F70 -> 0.15629773 | I70: 5.8 | J70: -0.15 | K70: =I70/C70 -> 3.3526012 | L70: =I70+F70*J70 -> 4.2805 | M70: =W70/E70 -> 1.5332012 | N70: =L70/F70 -> 0.42255676 | O70: =U70/E70 -> 1.5332012 | P70: =D70*E70/W70 -> 1.0326733 | Q70: 11.21 | R70: 8.33 | S70: 4.66 | T70: 77.36 | U70: 77.35 | V70: =U70/T70 -> 0.99987073 | W70: 77.35 | X70: 0.45 | Y70: 4.32 | Z70: 0 | AA70: 0 | AB70: 334 | AC70: 4.39 | AD70: 1.27 | AE70: 167 | AF70: 5.11 | AH70: 9.3 | AI70: 0 | AJ70: 552 | AK70: 519 | AL70: 199 | AM70: 32 | AN70: =AJ70-AM70 -> 520 | AO70: -10 | AP70: 0.3 | AQ70: 0.3 | AR70: 2.2 | AS70: =AVERAGE(AP70:AR70) -> 0.93333333 | AT70: 16 | AU70: 13 | AV70: -10 | AW70: 120 | AX70: 72 | AY70: 77 | AZ70: =(AT70+AU70+AV70)/(AW70+AX70+AY70) -> 0.07063197 | BA70: =AVERAGE(AT70:AV70) -> 6.3333333 | BB70: =BA70-AS70 -> 5.4 | BC70: =AB70+AE70-AH70-AI70 -> 491.7 | BD70: =BC70/AS70 -> 526.82143 | BE70: =BC70/G70 -> 6.1556926 | BF70: =A70 -> 华晨中国
A71: 华晨中国 | B71: 2024年报 | C71: 3.8 | D71: =C71*$B$2 -> 3.47776 | E71: 50.45 | F71: 5.17 | G71: =D71*E71 -> 175.45299 | H71: =D71/F71 -> 0.67268085 | I71: 1 | J71: =F71/F70-1 -> -0.48963475 | K71: =I71/C71 -> 0.26315789 | L71: =I71+F71*J71 -> -1.5314116 | M71: =W71/E71 -> 0.61446977 | N71: =L71/F71 -> -0.29621115 | O71: =U71/E71 -> 0.61446977 | P71: =D71*E71/W71 -> 5.6597739 | Q71: 11 | R71: 9 | S71: 1.6 | T71: 30.5 | U71: 31 | V71: =U71/T71 -> 1.0163934 | W71: 31 | X71: 0.45 | Y71: 5.3 | Z71: 0 | AA71: 0 | AB71: 112 | AC71: 4.86 | AD71: 2.61 | AE71: 125 | AF71: 5.4 | AH71: 6.1 | AI71: 0 | AJ71: 291 | AK71: 271 | AL71: 157 | AM71: 18 | AN71: =AJ71-AM71 -> 273 | AO71: -2.14 | AP71: 1.43 | AQ71: 0.3 | AR71: 0.3 | AS71: =AVERAGE(AP71:AR71) -> 0.67666667 | AT71: -2.14 | AU71: 13 | AV71: -10 | AW71: 30 | AX71: 72 | AY71: 77 | AZ71: =(AT71+AU71+AV71)/(AW71+AX71+AY71) -> 0.0048044693 | BA71: =AVERAGE(AT71:AV71) -> 0.28666667 | BB71: =BA71-AS71 -> -0.39 | BC71: =AB71+AE71-AH71-AI71 -> 230.9 | BD71: =BC71/AS71 -> 341.23153 | BE71: =BC71/G71 -> 1.316022 | BF71: =A71 -> 华晨中国
A72: 江南布衣 | B72: 2024年报 | C72: 18.3 | D72: =C72*$B$2 -> 16.74816 | E72: 5.19 | F72: 5.01 | G72: =D72*E72 -> 86.92295 | H72: =C72/F72 -> 3.6526946 | I72: 1.3 | J72: 0.1 | K72: =I72/C72 -> 0.071038251 | L72: =I72+F72*J72 -> 1.801 | M72: =W72/E72 -> 1.6358382 | N72: =L72/F72 -> 0.35948104 | O72: =U72/E72 -> 1.6358382 | P72: =D72*E72/W72 -> 10.238274 | Q72: 52.4 | R72: 17.68 | S72: 12.15 | T72: 8.48 | U72: 8.49 | V72: =U72/T72 -> 1.0011792 | W72: 8.49 | X72: 18.27 | Y72: 5.07 | Z72: 0 | AA72: 0.4 | AB72: 17.2 | AC72: 2.23 | AD72: 9.91 | AE72: 1.94 | AF72: 4.18 | AH72: 2.48 | AI72: 1.82 | AJ72: 51 | AK72: 24.55 | AL72: 18 | AM72: 18 | AN72: =AJ72-AM72 -> 33 | AO72: 16 | AP72: 1.03 | AQ72: 0.5 | AR72: 0.7 | AS72: =AVERAGE(AP72:AR72) -> 0.74333333 | AT72: 16 | AU72: 9.39 | AV72: 8.53 | AW72: 8.49 | AX72: 6.21 | AY72: 5.59 | AZ72: =(AT72+AU72+AV72)/(AW72+AX72+AY72) -> 1.6717595 | BA72: =AVERAGE(AT72:AV72) -> 11.306667 | BB72: =BA72-AS72 -> 10.563333 | BC72: =AB72+AE72-AH72-AI72 -> 14.84 | BD72: =BC72/AS72 -> 19.964126 | BE72: =BC72/G72 -> 0.17072591 | BF72: =A72 -> 江南布衣
A73: 波司登 | B73: 2024年报 | C73: 4.56 | D73: =C73*$B$2 -> 4.173312 | E73: 115.44 | F73: 1.59 | G73: =D73*E73 -> 481.76714 | H73: =C73/F73 -> 2.8679245 | I73: 0.249 | J73: =1.59/1.33-1 -> 0.19548872 | K73: =I73/C73 -> 0.054605263 | L73: =I73+F73*J73 -> 0.55982707 | M73: =W73/E73 -> 0.30405405 | N73: =L73/F73 -> 0.3520925 | O73: =U73/E73 -> 0.30405405 | P73: =D73*E73/W73 -> 13.725559 | Q73: 259 | R73: 111 | S73: 52 | T73: 35.5 | U73: 35.1 | V73: =U73/T73 -> 0.98873239 | W73: 35.1 | X73: 85 | Y73: 16.5 | Z73: 0 | AA73: 1.67 | AB73: 120 | AC73: 12 | AD73: 39.5 | AE73: 9.86 | AF73: 52 | AH73: 13.47 | AI73: 5.12 | AJ73: 274 | AK73: 170 | AL73: 82 | AM73: 95 | AN73: =AJ73-AM73 -> 179 | AO73: 30.5 | AP73: 5.6 | AQ73: 5.1 | AR73: 5.8 | AS73: =AVERAGE(AP73:AR73) -> 5.5 | AT73: 30.5 | AU73: 26.7 | AV73: 31.3 | AW73: 35.5 | AX73: 11.42 | AY73: 31.2 | AZ73: =(AT73+AU73+AV73)/(AW73+AX73+AY73) -> 1.1328725 | BA73: =AVERAGE(AT73:AV73) -> 29.5 | BB73: =BA73-AS73 -> 24 | BC73: =AB73+AE73-AH73-AI73 -> 111.27 | BD73: =BC73/AS73 -> 20.230909 | BE73: =BC73/G73 -> 0.2309622 | BF73: =A73 -> 波司登
A74: 华润医药 | B74: 2024年报 | C74: 5.21 | D74: =C74*$B$2 -> 4.768192 | E74: 62.83 | F74: 7.68 | G74: =D74*E74 -> 299.5855 | H74: =C74/F74 -> 0.67838542 | I74: 0.148 | J74: 0.05 | K74: =I74/C74 -> 0.02840691 | L74: =I74+F74*J74 -> 0.532 | M74: =W74/E74 -> 0.55865033 | N74: =L74/F74 -> 0.069270833 | O74: =U74/E74 -> 0.53318478 | P74: =D74*E74/W74 -> 8.5351995 | Q74: 2577 | R74: 2170 | S74: 105 | T74: 84 | U74: 33.5 | V74: =U74/T74 -> 0.39880952 | W74: 35.1 | X74: 198 | Y74: 67 | Z74: 0 | AA74: 22.82 | AB74: 530 | AC74: 818 | AD74: 371 | AE74: 61 | AF74: 586 | AH74: 454 | AI74: 236 | AJ74: 2577 | AK74: 981 | AL74: 719 | AM74: 1322 | AN74: =AJ74-AM74 -> 1255 | AO74: 175 | AP74: 27.7 | AQ74: 26.5 | AR74: 24 | AS74: =AVERAGE(AP74:AR74) -> 26.066667 | AT74: 156 | AU74: 108 | AV74: 128 | AW74: 84 | AX74: 78 | AY74: 67 | AZ74: =(AT74+AU74+AV74)/(AW74+AX74+AY74) -> 1.7117904 | BA74: =AVERAGE(AT74:AV74) -> 130.66667 | BB74: =BA74-AS74 -> 104.6 | BC74: =AB74+AE74-AH74-AI74 -> -99 | BD74: =BC74/AS74 -> -3.797954 | BE74: =BC74/G74 -> -0.33045658 | BF74: =A74 -> 华润医药
A75: 京东健康 | B75: 2024年报 | C75: 57.3 | D75: =C75*$B$2 -> 52.44096 | E75: 32 | F75: 18.82 | G75: =D75*E75 -> 1678.1107 | H75: =C75/F75 -> 3.0446334 | I75: 0 | J75: 0.1 | K75: =I75/C75 -> 0 | L75: =I75+F75*J75 -> 1.882 | M75: =W75/E75 -> 1.3125 | N75: =L75/F75 -> 0.1 | O75: =U75/E75 -> 1.3125 | P75: =D75*E75/W75 -> 39.955017 | Q75: 582 | R75: 449 | S75: 49 | T75: 42 | U75: 42 | V75: =U75/T75 -> 1 | W75: 42 | X75: 91 | Y75: 14 | Z75: 13.3 | AA75: 0.08 | AB75: 482 | AC75: 5.5 | AD75: 58 | AE75: 14.3 | AF75: 104 | AH75: 1.1 | AI75: 1.5 | AJ75: 713 | AK75: 552 | AL75: 128 | AM75: 155 | AN75: =AJ75-AM75 -> 558 | AO75: 43 | AP75: 0.5 | AQ75: 0.7 | AR75: 0.4 | AS75: =AVERAGE(AP75:AR75) -> 0.53333333 | AT75: 59 | AU75: 46 | AV75: 43 | AW75: 42 | AX75: 21 | AY75: 3.8 | AZ75: =(AT75+AU75+AV75)/(AW75+AX75+AY75) -> 2.2155689 | BA75: =AVERAGE(AT75:AV75) -> 49.333333 | BB75: =BA75-AS75 -> 48.8 | BC75: =AB75+AE75-AH75-AI75 -> 493.7 | BD75: =BC75/AS75 -> 925.6875 | BE75: =BC75/G75 -> 0.2941999 | BF75: =A75 -> 京东健康
A76: 阿里健康 | B76: 2024年报 | C76: 5.92 | D76: =C76*$B$2 -> 5.417984 | E76: 161.24 | F76: 1.11 | G76: =D76*E76 -> 873.59574 | H76: =C76/F76 -> 5.3333333 | I76: 0 | J76: 0 | K76: =I76/C76 -> 0 | L76: =I76+F76*J76 -> 0 | M76: =W76/E76 -> 0.088687671 | N76: =L76/F76 -> 0 | O76: =U76/E76 -> 0.088687671 | P76: =D76*E76/W76 -> 61.090611 | Q76: 306 | R76: 232 | S76: 16.3 | T76: 14.3 | U76: 14.3 | V76: =U76/T76 -> 1 | W76: 14.3 | X76: 22.6 | Y76: 30 | Z76: 7.2 | AA76: 0.03 | AB76: 84 | AC76: 10.5 | AD76: 15.2 | AE76: 34.5 | AF76: 28.5 | AH76: 0.1 | AI76: 0.3 | AJ76: 212 | AK76: 163 | AL76: 89 | AM76: 48 | AN76: =AJ76-AM76 -> 164 | AO76: 14 | AP76: 0.2 | AQ76: 0.2 | AR76: 0.6 | AS76: =AVERAGE(AP76:AR76) -> 0.33333333 | AT76: 2.6 | AU76: 10.8 | AV76: 14 | AW76: 14.3 | AX76: 8.8 | AY76: 5.4 | AZ76: =(AT76+AU76+AV76)/(AW76+AX76+AY76) -> 0.96140351 | BA76: =AVERAGE(AT76:AV76) -> 9.1333333 | BB76: =BA76-AS76 -> 8.8 | BC76: =AB76+AE76-AH76-AI76 -> 118.1 | BD76: =BC76/AS76 -> 354.3 | BE76: =BC76/G76 -> 0.13518839 | BF76: =A76 -> 阿里健康
A77: 万物云 | B77: 2024年报 | C77: 25.24 | D77: =C77*$B$2 -> 23.099648 | E77: 11.56 | F77: 14.69 | G77: =D77*E77 -> 267.03193 | H77: =C77/F77 -> 1.7181756 | I77: 2.086 | J77: 0 | K77: =I77/C77 -> 0.082646593 | L77: =I77+F77*J77 -> 2.086 | M77: =W77/E77 -> 0.99480969 | N77: =L77/F77 -> 0.14200136 | O77: =U77/E77 -> 0.99480969 | P77: =D77*E77/W77 -> 23.220168 | Q77: 362 | R77: 315 | S77: 17.3 | T77: 12.56 | U77: 11.5 | V77: =U77/T77 -> 0.9156051 | W77: 11.5 | X77: 5.85 | Y77: 19.43 | Z77: 0 | AA77: 0.12 | AB77: 141 | AC77: 65.44 | AD77: 1 | AE77: 23 | AF77: 66.72 | AH77: 1.15 | AI77: 7.96 | AJ77: 398 | AK77: 177 | AL77: 159 | AM77: 192 | AN77: =AJ77-AM77 -> 206 | AO77: 19.2 | AP77: 2.25 | AQ77: 2.88 | AR77: 3.02 | AS77: =AVERAGE(AP77:AR77) -> 2.7166667 | AT77: 19.2 | AU77: 25.9 | AV77: 27.6 | AW77: 12.56 | AX77: 20.36 | AY77: 15.87 | AZ77: =(AT77+AU77+AV77)/(AW77+AX77+AY77) -> 1.4900594 | BA77: =AVERAGE(AT77:AV77) -> 24.233333 | BB77: =BA77-AS77 -> 21.516667 | BC77: =AB77+AE77-AH77-AI77 -> 154.89 | BD77: =BC77/AS77 -> 57.014724 | BE77: =BC77/G77 -> 0.58004299 | BF77: =A77 -> 万物云
A78: 中远海控 | B78: 2024年报 | C78: 12.49 | D78: =C78*$B$2 -> 11.430848 | E78: 154.9 | F78: 16.38 | G78: =D78*E78 -> 1770.6384 | H78: =C78/F78 -> 0.76251526 | I78: 1.73 | J78: 0.1 | K78: =I78/C78 -> 0.13851081 | L78: =I78+F78*J78 -> 3.368 | M78: =W78/E78 -> 3.1762427 | N78: =L78/F78 -> 0.20561661 | O78: =U78/E78 -> 3.1762427 | P78: =D78*E78/W78 -> 3.5988584 | Q78: 2339 | R78: 1662 | S78: 620 | T78: 556 | U78: 492 | V78: =U78/T78 -> 0.88489209 | W78: 492 | X78: 0 | Y78: 0 | Z78: 0 | AA78: 32 | AB78: 1851 | AC78: 89 | AD78: 63 | AE78: 782 | AF78: 156 | AH78: 137 | AI78: 626 | AJ78: 4975 | AK78: 2851 | AL78: 2914 | AM78: 1228 | AN78: =AJ78-AM78 -> 3747 | AO78: 693 | AP78: 256 | AQ78: 152 | AR78: 105 | AS78: =AVERAGE(AP78:AR78) -> 171 | AT78: 1968 | AU78: 226 | AV78: 693 | AW78: 556 | AX78: 284 | AY78: 1315 | AZ78: =(AT78+AU78+AV78)/(AW78+AX78+AY78) -> 1.3396752 | BA78: =AVERAGE(AT78:AV78) -> 962.33333 | BB78: =BA78-AS78 -> 791.33333 | BC78: =AB78+AE78-AH78-AI78 -> 1870 | BD78: =BC78/AS78 -> 10.935673 | BE78: =BC78/G78 -> 1.0561163 | BF78: =A78 -> 中远海控
A79: 中广核 | B79: 2024年报 | C79: 3.15 | D79: =C79*$B$2 -> 2.88288 | E79: 504.99 | F79: =2.68*B2 -> 2.452736 | G79: =D79*E79 -> 1455.8256 | H79: =D79/F79 -> 1.1753731 | I79: 0.104 | J79: 0.055 | K79: =I79/C79 -> 0.033015873 | L79: =I79+F79*J79 -> 0.23890048 | M79: =W79/E79 -> 0.21188538 | N79: =L79/F79 -> 0.097401628 | O79: =U79/E79 -> 0.21386562 | P79: =D79*E79/W79 -> 13.605846 | Q79: 868 | R79: 582 | S79: 201 | T79: 174 | U79: 108 | V79: =U79/T79 -> 0.62068966 | W79: 107 | X79: 0.5 | Y79: 26.8 | Z79: 24.4 | AA79: 55.25 | AB79: 168 | AC79: 92 | AD79: 203 | AE79: 162 | AF79: 269 | AG79: 1.68 | AH79: 173 | AI79: 1558 | AJ79: 4267 | AK79: 1735 | AL79: 3511 | AM79: 835 | AN79: =AJ79-AM79 -> 3432 | AO79: 380 | AP79: 197 | AQ79: 142 | AR79: 118 | AS79: =AVERAGE(AP79:AR79) -> 152.33333 | AT79: 314 | AU79: 331 | AV79: 380 | AW79: 174 | AX79: 170 | AY79: 152 | AZ79: =(AT79+AU79+AV79)/(AW79+AX79+AY79) -> 2.0665323 | BA79: =AVERAGE(AT79:AV79) -> 341.66667 | BB79: =BA79-AS79 -> 189.33333 | BC79: =AB79+AE79-AH79-AI79 -> -1401 | BD79: =BC79/AS79 -> -9.1969365 | BE79: =BC79/G79 -> -0.96234056 | BF79: =A79 -> 中广核
A80: 第一拖拉机 | B80: 2024年报 | C80: 7.93 | D80: =C80*$B$2 -> 7.257536 | E80: 11.24 | F80: 7.64 | G80: =D80*E80 -> 81.574705 | H80: =C80/F80 -> 1.0379581 | I80: 0.402 | J80: 0.085 | K80: =I80/C80 -> 0.050693569 | L80: =I80+F80*J80 -> 1.0514 | M80: =W80/E80 -> 0.77135231 | N80: =L80/F80 -> 0.1376178 | O80: =U80/E80 -> 0.8202847 | P80: =D80*E80/W80 -> 9.4088471 | Q80: 119 | R80: 102 | S80: 10.4 | T80: 9.3 | U80: 9.22 | V80: =U80/T80 -> 0.99139785 | W80: 8.67 | X80: 1.56 | Y80: 3.55 | Z80: 5.16 | AA80: 0.1 | AB80: 37 | AC80: 3.39 | AD80: 13.75 | AE80: 7.3 | AF80: 47 | AG80: 0.1 | AH80: 0 | AI80: 0.6 | AJ80: 147 | AK80: 78 | AL80: 73 | AM80: 65 | AN80: =AJ80-AM80 -> 82 | AO80: 12.16 | AP80: 1.12 | AQ80: 0.9 | AR80: 0.9 | AS80: =AVERAGE(AP80:AR80) -> 0.97333333 | AT80: 15 | AU80: 11 | AV80: 12.2 | AW80: 9.3 | AX80: 9.9 | AY80: 6.4 | AZ80: =(AT80+AU80+AV80)/(AW80+AX80+AY80) -> 1.4921875 | BA80: =AVERAGE(AT80:AV80) -> 12.733333 | BB80: =BA80-AS80 -> 11.76 | BC80: =AB80+AE80-AH80-AI80 -> 43.7 | BD80: =BC80/AS80 -> 44.89726 | BE80: =BC80/G80 -> 0.53570528 | BF80: =A80 -> 第一拖拉机
A81: 药明生物 | B81: 2024年报 | C81: 33.24 | D81: =C81*$B$2 -> 30.421248 | E81: 40.79 | F81: 12.09 | G81: =D81*E81 -> 1240.8827 | H81: =C81/F81 -> 2.7493797 | I81: 0 | J81: 0.075 | K81: =I81/C81 -> 0 | L81: =I81+F81*J81 -> 0.90675 | M81: =W81/E81 -> 0.82373131 | N81: =L81/F81 -> 0.075 | O81: =U81/E81 -> 0.82373131 | P81: =D81*E81/W81 -> 36.931033 | Q81: 187 | R81: 110 | S81: 48 | T81: 39.5 | U81: 33.6 | V81: =U81/T81 -> 0.85063291 | W81: 33.6 | X81: 4.7 | Y81: 17.2 | Z81: 7.7 | AA81: 1.6 | AB81: 107 | AC81: 55.3 | AD81: 15.22 | AE81: 24 | AF81: 7.5 | AH81: 26.2 | AI81: 23.2 | AJ81: 560 | AK81: 418 | AL81: 236 | AM81: 86 | AN81: =AJ81-AM81 -> 474 | AO81: 52.2 | AP81: 39 | AQ81: 42 | AR81: 59 | AS81: =AVERAGE(AP81:AR81) -> 46.666667 | AT81: 55 | AU81: 47 | AV81: 52 | AW81: 39.5 | AX81: 35.7 | AY81: 45.5 | AZ81: =(AT81+AU81+AV81)/(AW81+AX81+AY81) -> 1.2758906 | BA81: =AVERAGE(AT81:AV81) -> 51.333333 | BB81: =BA81-AS81 -> 4.6666667 | BC81: =AB81+AE81-AH81-AI81 -> 81.6 | BD81: =BC81/AS81 -> 1.7485714 | BE81: =BC81/G81 -> 0.06575964 | BF81: =A81 -> 药明生物
A82: 海天国际 | B82: 2024年报 | C82: 22 | D82: =C82*$B$2 -> 20.1344 | E82: 15.96 | F82: 14.86 | G82: =D82*E82 -> 321.34502 | H82: =C82/F82 -> 1.4804845 | I82: 0.73 | J82: 0.1 | K82: =I82/C82 -> 0.033181818 | L82: =I82+F82*J82 -> 2.216 | M82: =W82/E82 -> 1.9298246 | N82: =L82/F82 -> 0.14912517 | O82: =U82/E82 -> 1.9298246 | P82: =D82*E82/W82 -> 10.43328 | Q82: 161 | R82: 109 | S82: 37 | T82: 30.8 | U82: 30.8 | V82: =U82/T82 -> 1 | W82: 30.8 | X82: 12.76 | Y82: 10.4 | Z82: 0 | AA82: 0.7 | AB82: 90 | AC82: 37 | AD82: 46 | AE82: 31 | AF82: 46 | AH82: 0.2 | AI82: 20.7 | AJ82: 311 | AK82: 209 | AL82: 134 | AM82: 79 | AN82: =AJ82-AM82 -> 232 | AO82: 21 | AP82: 11.8 | AQ82: 11.2 | AR82: 15 | AS82: =AVERAGE(AP82:AR82) -> 12.666667 | AT82: 17.8 | AU82: 20.1 | AV82: 21 | AW82: 31 | AX82: 25 | AY82: 23 | AZ82: =(AT82+AU82+AV82)/(AW82+AX82+AY82) -> 0.74556962 | BA82: =AVERAGE(AT82:AV82) -> 19.633333 | BB82: =BA82-AS82 -> 6.9666667 | BC82: =AB82+AE82-AH82-AI82 -> 100.1 | BD82: =BC82/AS82 -> 7.9026316 | BE82: =BC82/G82 -> 0.31150319 | BF82: =A82 -> 海天国际
A84: 大秦铁路 | B84: 2023年报 | D84: 6.67 | E84: 176.19 | F84: 8.56 | G84: =D84*E84 -> 1175.1873 | H84: =D84/F84 -> 0.77920561 | I84: 0.38193 | J84: 0.03 | K84: =I84/D84 -> 0.05726087 | L84: =I84+F84*J84 -> 0.63873 | M84: =W84/E84 -> 0.68108292 | N84: =L84/F84 -> 0.074617991 | O84: =U84/E84 -> 0.67540723 | P84: =D84*E84/W84 -> 9.7932275 | Q84: 810 | R84: 658 | S84: 179 | T84: 136 | U84: 119 | V84: =U84/T84 -> 0.875 | W84: 120 | X84: 2.3 | Y84: 8.38 | Z84: 0.1 | AA84: 16.4 | AB84: 682 | AE84: 251 | AH84: 0.4 | AI84: 107 | AJ84: 2077 | AK84: 1524 | AL84: 1318 | AM84: 153 | AN84: =AJ84-AM84 -> 1924 | AO84: 172 | AP84: 73 | AS84: =AVERAGE(AP84:AR84) -> 73 | AT84: 189 | AU84: 161 | AV84: 172 | AW84: 122 | AX84: 112 | AY84: 119 | AZ84: =(AT84+AU84+AV84)/(AW84+AX84+AY84) -> 1.4787535 | BA84: =AVERAGE(AT84:AV84) -> 174 | BB84: =BA84-AS84 -> 101 | BC84: =AB84+AE84-AH84-AI84 -> 825.6 | BD84: =BC84/AS84 -> 11.309589 | BE84: =BC84/G84 -> 0.70252631 | BF84: =A84 -> 大秦铁路
A85: 格力电器 | B85: 2023年报 | D85: 40 | E85: 56.31 | F85: 20.74 | G85: =D85*E85 -> 2252.4 | H85: =D85/F85 -> 1.9286403 | I85: 2.38 | J85: 0.1 | K85: =I85/D85 -> 0.0595 | L85: =I85+F85*J85 -> 4.454 | M85: =W85/E85 -> 4.9014385 | N85: =L85/F85 -> 0.2147541 | O85: =U85/E85 -> 5.1500622 | P85: =D85*E85/W85 -> 8.1608696 | Q85: 2050 | R85: 1416 | S85: 329 | T85: 277 | U85: 290 | V85: =U85/T85 -> 1.0469314 | W85: 276 | X85: 148 | Y85: 65 | Z85: 68 | AA85: 29.6 | AB85: 1337 | AC85: 162 | AD85: 326 | AE85: 83.5 | AF85: 649 | AH85: 264 | AI85: 390 | AJ85: 3680 | AK85: 1206 | AL85: 1399 | AM85: 2009 | AN85: =AJ85-AM85 -> 1671 | AO85: 564 | AP85: 54 | AQ85: 60 | AR85: 57 | AS85: =AVERAGE(AP85:AR85) -> 57 | AT85: 19 | AU85: 287 | AV85: 564 | AW85: 230 | AX85: 245 | AY85: 290 | AZ85: =(AT85+AU85+AV85)/(AW85+AX85+AY85) -> 1.1372549 | BA85: =AVERAGE(AT85:AV85) -> 290 | BB85: =BA85-AS85 -> 233 | BC85: =AB85+AE85-AH85-AI85 -> 766.5 | BD85: =BC85/AS85 -> 13.447368 | BE85: =BC85/G85 -> 0.34030368 | BF85: =A85 -> 格力电器
A86: 格力电器 | B86: 2024年报 | D86: 40 | E86: 56.01 | F86: 24.53 | G86: =D86*E86 -> 2240.4 | H86: =D86/F86 -> 1.6306563 | I86: 3 | J86: =F86/F85-1 -> 0.18273867 | K86: =I86/D86 -> 0.075 | L86: =I86+F86*J86 -> 7.4825796 | M86: =W86/E86 -> 5.3740403 | N86: =L86/F86 -> 0.30503789 | O86: =U86/E86 -> 5.7489734 | P86: =D86*E86/W86 -> 7.4431894 | Q86: 1900 | R86: 1335 | S86: 370 | T86: 324 | U86: 322 | V86: =U86/T86 -> 0.99382716 | W86: 301 | X86: 98 | Y86: 61 | Z86: 69 | AA86: 23.8 | AB86: =1139+165 -> 1304 | AC86: 168 | AD86: 279 | AE86: =43.6+30.4 -> 74 | AF86: 616 | AH86: 390 | AI86: 182 | AJ86: 3680 | AK86: 1415 | AL86: 1432 | AM86: 2011 | AN86: =AJ86-AM86 -> 1669 | AO86: 294 | AP86: 33 | AQ86: 54 | AR86: 60 | AS86: =AVERAGE(AP86:AR86) -> 49 | AT86: 564 | AU86: 287 | AV86: 19 | AW86: 277 | AX86: 230 | AY86: 228 | AZ86: =(AT86+AU86+AV86)/(AW86+AX86+AY86) -> 1.1836735 | BA86: =AVERAGE(AT86:AV86) -> 290 | BB86: =BA86-AS86 -> 241 | BC86: =AB86+AE86-AH86-AI86 -> 806 | BD86: =BC86/AS86 -> 16.44898 | BE86: =BC86/G86 -> 0.35975719 | BF86: =A86 -> 格力电器
A87: 美的集团 | B87: 2023年报 | D87: 76.06 | E87: 69.75 | F87: 23.18 | G87: =D87*E87 -> 5305.185 | H87: =D87/F87 -> 3.281277 | I87: 3 | J87: 0.14 | K87: =I87/D87 -> 0.039442545 | L87: =I87+F87*J87 -> 6.2452 | M87: =W87/E87 -> 4.7311828 | N87: =L87/F87 -> 0.26942192 | O87: =U87/E87 -> 4.7885305 | P87: =D87*E87/W87 -> 16.076318 | Q87: 3737 | R87: 3350 | S87: 403 | T87: 337 | U87: 334 | V87: =U87/T87 -> 0.99109792 | W87: 330 | X87: 349 | Y87: 135 | Z87: 146 | AA87: 28 | AB87: =817+18 -> 835 | AC87: 329 | AD87: 473 | AE87: 50 | AF87: 942 | AH87: 88 | AI87: 462 | AJ87: 4860 | AK87: 1743 | AL87: 2047 | AM87: 2512 | AN87: =AJ87-AM87 -> 2348 | AO87: 579 | AP87: 63 | AQ87: 74 | AR87: 68 | AS87: =AVERAGE(AP87:AR87) -> 68.333333 | AT87: 294 | AU87: 564 | AV87: 287 | AW87: 324 | AX87: 277 | AY87: 230 | AZ87: =(AT87+AU87+AV87)/(AW87+AX87+AY87) -> 1.377858 | BA87: =AVERAGE(AT87:AV87) -> 381.66667 | BB87: =BA87-AS87 -> 313.33333 | BC87: =AB87+AE87-AH87-AI87 -> 335 | BD87: =BC87/AS87 -> 4.902439 | BE87: =BC87/G87 -> 0.063145772 | BF87: =A87 -> 美的集团
A88: 美的集团 | B88: 2024年报 | D88: 74.4 | E88: 76.6 | F88: 28.31 | G88: =D88*E88 -> 5699.04 | H88: =D88/F88 -> 2.6280466 | I88: 3.5 | J88: =F88/F87-1 -> 0.22131148 | K88: =I88/D88 -> 0.047043011 | L88: =I88+F88*J88 -> 9.7653279 | M88: =W88/E88 -> 4.6605744 | N88: =L88/F88 -> 0.3449427 | O88: =U88/E88 -> 5.0261097 | P88: =D88*E88/W88 -> 15.963697 | Q88: 4091 | R88: 3678 | S88: 464 | T88: 388 | U88: 385 | V88: =U88/T88 -> 0.99226804 | W88: 357 | X88: 388 | Y88: 145 | Z88: 162 | AA88: 25 | AB88: 1470 | AC88: 358 | AD88: 633 | AE88: 52 | AF88: 1188 | AH88: 310 | AI88: 105 | AJ88: 6043 | AK88: 2277 | AL88: 2153 | AM88: 3518 | AN88: =AJ88-AM88 -> 2525 | AO88: 605 | AP88: 78 | AQ88: 63 | AR88: 74 | AS88: =AVERAGE(AP88:AR88) -> 71.666667 | AT88: 605 | AU88: 579 | AV88: 347 | AW88: 388 | AX88: 338 | AY88: 298 | AZ88: =(AT88+AU88+AV88)/(AW88+AX88+AY88) -> 1.4951172 | BA88: =AVERAGE(AT88:AV88) -> 510.33333 | BB88: =BA88-AS88 -> 438.66667 | BC88: =AB88+AE88-AH88-AI88 -> 1107 | BD88: =BC88/AS88 -> 15.446512 | BE88: =BC88/G88 -> 0.19424324 | BF88: =A88 -> 美的集团
A89: 海尔智家 | B89: 2023年报 | D89: 28.06 | E89: 94.38 | F89: 10.97 | G89: =D89*E89 -> 2648.3028 | H89: =D89/F89 -> 2.5578851 | I89: 0.804 | J89: 0.14 | K89: =I89/D89 -> 0.028652887 | L89: =I89+F89*J89 -> 2.3398 | M89: =W89/E89 -> 1.6740835 | N89: =L89/F89 -> 0.21329079 | O89: =U89/E89 -> 1.6740835 | P89: =D89*E89/W89 -> 16.76141 | Q89: 2742 | R89: 1988 | S89: 204 | T89: 171 | U89: 158 | V89: =U89/T89 -> 0.92397661 | W89: 158 | X89: 327 | Y89: 119 | Z89: 104 | AA89: 22 | AB89: =572+10 -> 582 | AC89: 315 | AD89: 395 | AE89: 266 | AF89: 722 | AH89: 109 | AI89: 184 | AJ89: 2610 | AK89: 1012 | AL89: 1221 | AM89: 1238 | AN89: =AJ89-AM89 -> 1372 | AO89: 265 | AP89: 105 | AQ89: 82 | AR89: 74 | AS89: =AVERAGE(AP89:AR89) -> 87 | AT89: 232 | AU89: 203 | AV89: 265 | AW89: 132 | AX89: 147 | AY89: 171 | AZ89: =(AT89+AU89+AV89)/(AW89+AX89+AY89) -> 1.5555556 | BA89: =AVERAGE(AT89:AV89) -> 233.33333 | BB89: =BA89-AS89 -> 146.33333 | BC89: =AB89+AE89-AH89-AI89 -> 555 | BD89: =BC89/AS89 -> 6.3793103 | BE89: =BC89/G89 -> 0.20956818 | BF89: =A89 -> 海尔智家
A90: 海尔智家 | B90: 2024年报 | D90: 26.81 | E90: 93.8 | F90: 12.74 | G90: =D90*E90 -> 2514.778 | H90: =D90/F90 -> 2.1043956 | I90: 1.234 | J90: 0.08 | K90: =I90/D90 -> 0.046027602 | L90: =I90+F90*J90 -> 2.2532 | M90: =W90/E90 -> 1.8976546 | N90: =L90/F90 -> 0.17686028 | O90: =U90/E90 -> 1.8976546 | P90: =D90*E90/W90 -> 14.127966 | Q90: 2860 | R90: 2065 | S90: 229 | T90: 196 | U90: 178 | V90: =U90/T90 -> 0.90816327 | W90: 178 | X90: 336 | Y90: 121 | Z90: 107 | AA90: 27 | AB90: =556+12 -> 568 | AC90: 386 | AD90: 430 | AE90: 269 | AF90: 757 | AG90: 0.3 | AH90: 138 | AI90: 97 | AJ90: 2901 | AK90: 1114 | AL90: 1386 | AM90: 1498 | AN90: =AJ90-AM90 -> 1403 | AO90: 265 | AP90: 101 | AQ90: 105 | AR90: 82 | AS90: =AVERAGE(AP90:AR90) -> 96 | AT90: 203 | AU90: 265 | AV90: 265 | AW90: 147 | AX90: 171 | AY90: 196 | AZ90: =(AT90+AU90+AV90)/(AW90+AX90+AY90) -> 1.42607 | BA90: =AVERAGE(AT90:AV90) -> 244.33333 | BB90: =BA90-AS90 -> 148.33333 | BC90: =AB90+AE90-AH90-AI90 -> 602 | BD90: =BC90/AS90 -> 6.2708333 | BE90: =BC90/G90 -> 0.23938495 | BF90: =A90 -> 海尔智家
A91: 鱼跃医疗 | B91: 2023年报 | D91: 36 | E91: 10.02 | F91: 11.73 | G91: =D91*E91 -> 360.72 | H91: =D91/F91 -> 3.0690537 | I91: 0.8 | J91: 0.15 | K91: =I91/D91 -> 0.022222222 | L91: =I91+F91*J91 -> 2.5595 | M91: =W91/E91 -> 1.9101278 | N91: =L91/F91 -> 0.21820119 | O91: =U91/E91 -> 2.3912176 | P91: =D91*E91/W91 -> 18.846907 | Q91: 79.7 | R91: 38.67 | S91: 28.93 | T91: 23.76 | U91: 23.96 | V91: =U91/T91 -> 1.0084175 | W91: =(28.49-5.55)*(28.49-4.72)/28.49 -> 19.139481 | X91: 10.98 | Y91: 4.11 | Z91: 5.04 | AA91: 0.58 | AB91: 72 | AC91: 4.48 | AD91: 14.12 | AE91: 2.26 | AF91: 14.11 | AH91: 0 | AI91: 6.8 | AJ91: 159 | AK91: 119 | AL91: 65.8 | AM91: 28.7 | AN91: =AJ91-AM91 -> 130.3 | AO91: 21.27 | AP91: 1.33 | AQ91: 3.79 | AR91: 2.84 | AS91: =AVERAGE(AP91:AR91) -> 2.6533333 | AT91: 12 | AU91: 23 | AV91: 21 | AW91: 15 | AX91: 16 | AY91: 24 | AZ91: =(AT91+AU91+AV91)/(AW91+AX91+AY91) -> 1.0181818 | BA91: =AVERAGE(AT91:AV91) -> 18.666667 | BB91: =BA91-AS91 -> 16.013333 | BC91: =AB91+AE91-AH91-AI91 -> 67.46 | BD91: =BC91/AS91 -> 25.424623 | BE91: =BC91/G91 -> 0.18701486 | BF91: =A91 -> 鱼跃医疗
A92: 鱼跃医疗 | B92: 2024年报 | D92: 35.22 | E92: 10.02 | F92: 12.5 | G92: =D92*E92 -> 352.9044 | H92: =D92/F92 -> 2.8176 | I92: 0.8 | J92: =F92/F91-1 -> 0.065643649 | K92: =I92/D92 -> 0.022714367 | L92: =I92+F92*J92 -> 1.6205456 | M92: =W92/E92 -> 1.3972056 | N92: =L92/F92 -> 0.12964365 | O92: =U92/E92 -> 1.7964072 | P92: =D92*E92/W92 -> 25.207457 | Q92: 75.7 | R92: 37.7 | S92: 18.3 | T92: 18 | U92: 18 | V92: =U92/T92 -> 1 | W92: 14 | X92: 13.6 | Y92: 4.28 | Z92: 5.47 | AA92: 0.2 | AB92: 66.2 | AC92: 7.15 | AD92: 14.4 | AE92: 0.7 | AF92: 15.29 | AH92: 0 | AI92: 0 | AJ92: 156 | AK92: 126.5 | AL92: 63.9 | AM92: 26.9 | AN92: =AJ92-AM92 -> 129.1 | AO92: 18.16 | AP92: 1.33 | AQ92: 3.79 | AR92: 1.28 | AS92: =AVERAGE(AP92:AR92) -> 2.1333333 | AT92: 18 | AU92: 23 | AV92: 21 | AW92: 18 | AX92: 16 | AY92: 24 | AZ92: =(AT92+AU92+AV92)/(AW92+AX92+AY92) -> 1.0689655 | BA92: =AVERAGE(AT92:AV92) -> 20.666667 | BB92: =BA92-AS92 -> 18.533333 | BC92: =AB92+AE92-AH92-AI92 -> 66.9 | BD92: =BC92/AS92 -> 31.359375 | BE92: =BC92/G92 -> 0.18956975 | BF92: =A92 -> 鱼跃医疗
A93: 迈瑞医疗 | B93: 2023年报 | D93: 223 | E93: 12.12 | F93: 32.2 | G93: =D93*E93 -> 2702.76 | H93: =D93/F93 -> 6.9254658 | I93: 4.93 | J93: 0.08 | K93: =I93/D93 -> 0.022107623 | L93: =I93+F93*J93 -> 7.506 | M93: =W93/E93 -> 9.4059406 | N93: =L93/F93 -> 0.23310559 | O93: =U93/E93 -> 9.6534653 | P93: =D93*E93/W93 -> 23.708421 | Q93: 367 | R93: 135 | S93: 131 | T93: 117 | U93: 117 | V93: =U93/T93 -> 1 | W93: 114 | X93: 53 | Y93: 16 | Z93: 37 | AA93: 0.2 | AB93: 166 | AC93: 32 | AD93: 48 | AE93: 2 | AF93: 28 | AH93: 0 | AI93: 0 | AJ93: 566 | AK93: 408 | AL93: 310 | AM93: 104 | AN93: 222 | AO93: 124 | AP93: 20 | AQ93: 27 | AR93: 19.2 | AS93: =AVERAGE(AP93:AR93) -> 22.066667 | AT93: 124 | AU93: 121 | AV93: 111 | AW93: 117 | AX93: 96 | AY93: 116 | AZ93: =(AT93+AU93+AV93)/(AW93+AX93+AY93) -> 1.0820669 | BA93: =AVERAGE(AT93:AV93) -> 118.66667 | BB93: =BA93-AS93 -> 96.6 | BC93: =AB93+AE93-AH93-AI93 -> 168 | BD93: =BC93/AS93 -> 7.6132931 | BE93: =BC93/G93 -> 0.062158682 | BF93: =A93 -> 迈瑞医疗
A94: 陕西煤业 | B94: 2023年报 | D94: 22 | E94: 96.95 | F94: 9.78 | G94: =D94*E94 -> 2132.9 | H94: =D94/F94 -> 2.2494888 | I94: 1.315 | J94: 0.1 | K94: =I94/D94 -> 0.059772727 | L94: =I94+F94*J94 -> 2.293 | M94: =W94/E94 -> 2.547705 | N94: =L94/F94 -> 0.23445808 | O94: =U94/E94 -> 2.1866942 | P94: =D94*E94/W94 -> 8.6352227 | Q94: 1709 | R94: 1062 | S94: 442 | T94: 359 | U94: 212 | V94: =U94/T94 -> 0.59052925 | W94: 247 | X94: 8.41 | Y94: 78 | Z94: 7.34 | AA94: 3.23 | AB94: 380 | AE94: 204 | AH94: 0 | AI94: 29 | AJ94: 1939 | AK94: 1241 | AL94: 1764 | AM94: 578 | AN94: =AJ94-AM94 -> 1361 | AO94: 424 | AP94: 139 | AQ94: 130 | AR94: 102 | AS94: =AVERAGE(AP94:AR94) -> 123.66667 | AT94: 526 | AU94: 561 | AV94: 386 | AW94: 214 | AX94: 352 | AY94: 212 | AZ94: =(AT94+AU94+AV94)/(AW94+AX94+AY94) -> 1.8933162 | BA94: =AVERAGE(AT94:AV94) -> 491 | BB94: =BA94-AS94 -> 367.33333 | BC94: =AB94+AE94-AH94-AI94 -> 555 | BD94: =BC94/AS94 -> 4.4878706 | BE94: =BC94/G94 -> 0.2602091 | BF94: =A94 -> 陕西煤业
A95: 中国神化 | B95: 2023年报 | D95: 43.6 | E95: 198.69 | F95: 20.57 | G95: =D95*E95 -> 8662.884 | H95: =D95/F95 -> 2.1195916 | I95: 2.26 | J95: 0.04 | K95: =I95/D95 -> 0.051834862 | L95: =I95+F95*J95 -> 3.0828 | M95: =W95/E95 -> 3.1657356 | N95: =L95/F95 -> 0.14986874 | O95: =U95/E95 -> 3.0046807 | P95: =D95*E95/W95 -> 13.772471 | Q95: 3431 | R95: 2199 | S95: 914 | T95: 696 | U95: 597 | V95: =U95/T95 -> 0.85775862 | W95: 629 | X95: 4.25 | Y95: 98 | Z95: 30 | AA95: 28.6 | AB95: 1500 | AC95: 199 | AD95: 128 | AE95: 580 | AF95: 389 | AH95: 30 | AI95: 300 | AJ95: 6300 | AK95: 4087 | AL95: 4311 | AM95: 916 | AN95: =AJ95-AM95 -> 5384 | AO95: 897 | AP95: 371 | AQ95: 287 | AR95: 236 | AS95: =AVERAGE(AP95:AR95) -> 298 | AT95: 943 | AU95: 1097 | AV95: 897 | AW95: 696 | AX95: 817 | AY95: 591 | AZ95: =(AT95+AU95+AV95)/(AW95+AX95+AY95) -> 1.3959125 | BA95: =AVERAGE(AT95:AV95) -> 979 | BB95: =BA95-AS95 -> 681 | BC95: =AB95+AE95-AH95-AI95 -> 1750 | BD95: =BC95/AS95 -> 5.8724832 | BE95: =BC95/G95 -> 0.20201125 | BF95: =A95 -> 中国神化
A96: 中国神化 | B96: 2024年报 | D96: 43 | E96: 198.69 | F96: 21.48 | G96: =D96*E96 -> 8543.67 | H96: =D96/F96 -> 2.0018622 | I96: 2.26 | J96: =F96/F95-1 -> 0.044239183 | K96: =I96/D96 -> 0.05255814 | L96: =I96+F96*J96 -> 3.2102577 | M96: =W96/E96 -> 3.0248125 | N96: =L96/F96 -> 0.14945334 | O96: =U96/E96 -> 2.954351 | P96: =D96*E96/W96 -> 14.215757 | Q96: 3384 | R96: 2231 | S96: 883.6 | T96: 688.65 | U96: 587 | V96: =U96/T96 -> 0.85239236 | W96: 601 | X96: 4.91 | Y96: 103.4 | Z96: 27.3 | AA96: 27 | AB96: =1424+173 -> 1597 | AC96: 155 | AD96: 125 | AE96: =598+28 -> 626 | AF96: 382 | AH96: 10 | AI96: 289 | AJ96: 6580 | AK96: 4268 | AL96: 4609 | AM96: 1051 | AN96: =AJ96-AM96 -> 5529 | AO96: 933 | AP96: 371 | AQ96: 370 | AR96: 287 | AS96: =AVERAGE(AP96:AR96) -> 342.66667 | AT96: 1097 | AU96: 897 | AV96: 933 | AW96: 689 | AX96: 696 | AY96: 817 | AZ96: =(AT96+AU96+AV96)/(AW96+AX96+AY96) -> 1.3292461 | BA96: =AVERAGE(AT96:AV96) -> 975.66667 | BB96: =BA96-AS96 -> 633 | BC96: =AB96+AE96-AH96-AI96 -> 1924 | BD96: =BC96/AS96 -> 5.614786 | BE96: =BC96/G96 -> 0.22519596 | BF96: =A96 -> 中国神化
A97: 五粮液 | B97: 2023年报 | D97: 118 | E97: 38.83 | F97: 37 | G97: =D97*E97 -> 4581.94 | H97: =D97/F97 -> 3.1891892 | I97: 4.67 | J97: 0.15 | K97: =I97/D97 -> 0.039576271 | L97: =I97+F97*J97 -> 10.22 | M97: =W97/E97 -> 7.7517383 | N97: =L97/F97 -> 0.27621622 | O97: =U97/E97 -> 7.7774916 | P97: =D97*E97/W97 -> 15.222392 | Q97: 833 | R97: 202 | S97: 420 | T97: 315 | U97: 302 | V97: =U97/T97 -> 0.95873016 | W97: 301 | X97: 78 | Y97: 33 | Z97: 3.22 | AA97: 0.1 | AB97: 1158 | AE97: 20 | AH97: 0 | AI97: 0 | AJ97: 1654 | AK97: 1323 | AL97: 225 | AM97: 510 | AN97: =AJ97-AM97 -> 1144 | AO97: 417 | AP97: 30 | AQ97: 18 | AR97: 15 | AS97: =AVERAGE(AP97:AR97) -> 21 | AT97: 268 | AU97: 244 | AV97: 417 | AW97: 234 | AX97: 267 | AY97: 302 | AZ97: =(AT97+AU97+AV97)/(AW97+AX97+AY97) -> 1.1569116 | BA97: =AVERAGE(AT97:AV97) -> 309.66667 | BB97: =BA97-AS97 -> 288.66667 | BC97: =AB97+AE97-AH97-AI97 -> 1178 | BD97: =BC97/AS97 -> 56.095238 | BE97: =BC97/G97 -> 0.25709634 | BF97: =A97 -> 五粮液
A98: 贵州茅台 | B98: 2023年报 | D98: 1432 | E98: 12.56 | F98: 190.84 | G98: =D98*E98 -> 17985.92 | H98: =D98/F98 -> 7.503668 | I98: 26 | J98: 0.1 | K98: =I98/D98 -> 0.018156425 | L98: =I98+F98*J98 -> 45.084 | M98: =W98/E98 -> 59.514331 | N98: =L98/F98 -> 0.23623978 | O98: =U98/E98 -> 59.474522 | P98: =D98*E98/W98 -> 24.061431 | Q98: 1506 | R98: 118.67 | S98: 1037 | T98: 775 | U98: 747 | V98: =U98/T98 -> 0.96387097 | W98: 747.5 | X98: 46.5 | Y98: 97.3 | Z98: 1.57 | AA98: 0.1 | AB98: 695 | AE98: 40 | AH98: 0 | AI98: 0 | AJ98: 2727 | AK98: 2157 | AL98: 472 | AM98: 565 | AN98: =AJ98-AM98 -> 2162 | AO98: 666 | AP98: 26 | AS98: =AVERAGE(AP98:AR98) -> 26 | AT98: 640 | AU98: 367 | AV98: 666 | AW98: 525 | AX98: 627 | AY98: 747 | AZ98: =(AT98+AU98+AV98)/(AW98+AX98+AY98) -> 0.88098999 | BA98: =AVERAGE(AT98:AV98) -> 557.66667 | BB98: =BA98-AS98 -> 531.66667 | BC98: =AB98+AE98-AH98-AI98 -> 735 | BD98: =BC98/AS98 -> 28.269231 | BE98: =BC98/G98 -> 0.040865299 | BF98: =A98 -> 贵州茅台
A99: 洋河股份 | B99: 2023年报 | D99: 65.7 | E99: 15.06 | F99: 38.49 | G99: =D99*E99 -> 989.442 | H99: =D99/F99 -> 1.7069369 | I99: 3.741 | J99: 0.1 | K99: =I99/D99 -> 0.056940639 | L99: =I99+F99*J99 -> 7.59 | M99: =W99/E99 -> 6.5073041 | N99: =L99/F99 -> 0.19719408 | O99: =U99/E99 -> 6.6401062 | P99: =D99*E99/W99 -> 10.096347 | Q99: 331 | R99: 82 | S99: 132 | T99: 100 | U99: 100 | V99: =U99/T99 -> 1 | W99: 98 | X99: 54 | Y99: 17.6 | Z99: 2.85 | AA99: 0 | AB99: 316 | AE99: 12.3 | AH99: 0 | AI99: 0 | AJ99: 698 | AK99: 521 | AL99: 170 | AM99: 153 | AN99: =AJ99-AM99 -> 545 | AO99: 61 | AP99: 11 | AS99: =AVERAGE(AP99:AR99) -> 11 | AT99: 153 | AU99: 36 | AV99: 61 | AW99: 75 | AX99: 94 | AY99: 100 | AZ99: =(AT99+AU99+AV99)/(AW99+AX99+AY99) -> 0.92936803 | BA99: =AVERAGE(AT99:AV99) -> 83.333333 | BB99: =BA99-AS99 -> 72.333333 | BC99: =AB99+AE99-AH99-AI99 -> 328.3 | BD99: =BC99/AS99 -> 29.845455 | BE99: =BC99/G99 -> 0.33180318 | BF99: =A99 -> 洋河股份
A100: 东鹏饮料 | B100: 2023年报 | D100: 263 | E100: 4 | F100: 15.81 | G100: =D100*E100 -> 1052 | H100: =D100/F100 -> 16.635041 | I100: 2.5 | J100: 0.225 | K100: =I100/D100 -> 0.0095057034 | L100: =I100+F100*J100 -> 6.05725 | M100: =W100/E100 -> 4.675 | N100: =L100/F100 -> 0.38312777 | O100: =U100/E100 -> 5.1 | P100: =D100*E100/W100 -> 56.256684 | Q100: 112 | R100: 64 | S100: 25.88 | T100: 20.4 | U100: 20.4 | V100: =U100/T100 -> 1 | W100: 18.7 | X100: 19.56 | Y100: 3.69 | Z100: 0.54 | AA100: 0.8 | AB100: 73 | AC100: 0.7 | AD100: 5.69 | AE100: 0 | AF100: 8.8 | AH100: 30 | AI100: 2.2 | AJ100: 147 | AK100: 63 | AL100: 59 | AM100: 80 | AN100: =AJ100-AM100 -> 67 | AO100: 32.8 | AP100: 9.18 | AQ100: 7.93 | AR100: 6.09 | AS100: =AVERAGE(AP100:AR100) -> 7.7333333 | AT100: 20.8 | AU100: 20.3 | AV100: 32.8 | AW100: 11.9 | AX100: 14.4 | AY100: 20.4 | AZ100: =(AT100+AU100+AV100)/(AW100+AX100+AY100) -> 1.5824411 | BA100: =AVERAGE(AT100:AV100) -> 24.633333 | BB100: =BA100-AS100 -> 16.9 | BC100: =AB100+AE100-AH100-AI100 -> 40.8 | BD100: =BC100/AS100 -> 5.2758621 | BE100: =BC100/G100 -> 0.03878327 | BF100: =A100 -> 东鹏饮料
A101: 东鹏饮料 | B101: 2024年报 | D101: 321.3 | E101: 5.2 | F101: 14.78 | G101: =D101*E101 -> 1670.76 | H101: =D101/F101 -> 21.738836 | I101: 5 | J101: =F101/F100-1 -> -0.06514864 | K101: =I101/D101 -> 0.01556178 | L101: =I101+F101*J101 -> 4.0371031 | M101: =W101/E101 -> 6.2730769 | N101: =L101/F101 -> 0.27314635 | O101: =U101/E101 -> 6.3980769 | P101: =D101*E101/W101 -> 51.218884 | Q101: 158 | R101: 87 | S101: 41 | T101: 33 | U101: 33.27 | V101: =U101/T101 -> 1.0081818 | W101: 32.62 | X101: 26.8 | Y101: 4.26 | Z101: 0.6 | AA101: 1 | AB101: 105 | AC101: 0.8 | AD101: 10.68 | AE101: 0 | AF101: 12.6 | AH101: 66 | AI101: 0 | AJ101: 227 | AK101: 77 | AL101: 100 | AM101: 148 | AN101: =AJ101-AM101 -> 79 | AO101: 58 | AP101: 16.9 | AQ101: 9.18 | AR101: 7.93 | AS101: =AVERAGE(AP101:AR101) -> 11.336667 | AT101: 20.3 | AU101: 32.8 | AV101: 58 | AW101: 14.4 | AX101: 20.4 | AY101: 33.3 | AZ101: =(AT101+AU101+AV101)/(AW101+AX101+AY101) -> 1.6314244 | BA101: =AVERAGE(AT101:AV101) -> 37.033333 | BB101: =BA101-AS101 -> 25.696667 | BC101: =AB101+AE101-AH101-AI101 -> 39 | BD101: =BC101/AS101 -> 3.4401647 | BE101: =BC101/G101 -> 0.02334267 | BF101: =A101 -> 东鹏饮料
...
